{
  "appInfo" : {
    "build" : "222.3345.118",
    "buildDate" : "2022-07-26T05:01:37.954Z[UTC]",
    "productCode" : "IC",
    "generated" : "2024-01-16T17:34:31.277545Z",
    "os" : "macOS 12.7.1",
    "runtime" : "JetBrains s.r.o. 17.0.3 17.0.3+7-b469.32"
  },
  "runtimeInfo" : {
    "maxMemory" : 786432000,
    "numberOfProcessors" : 8,
    "maxNumberOfIndexingThreads" : 4,
    "maxSizeOfFileForIntelliSense" : 2560000,
    "maxSizeOfFileForContentLoading" : 20971520
  },
  "projectIndexingHistory" : {
    "projectName" : "DiffVerificate",
    "times" : {
      "indexingReason" : "On project open",
      "scanningType" : "FULL_ON_PROJECT_OPEN",
      "totalUpdatingTime" : 164437320654,
      "indexingTime" : 154895517000,
      "contentLoadingVisibleTime" : 14941860670,
      "creatingIteratorsTime" : 8081000,
      "scanFilesTime" : 9487456000,
      "pushPropertiesTime" : 1144000,
      "indexExtensionsTime" : 0,
      "isAppliedAllValuesSeparately" : true,
      "separateApplyingIndexesVisibleTime" : 52097093201,
      "updatingStart" : "2024-01-16T17:31:46.82476Z",
      "updatingEnd" : "2024-01-16T17:34:31.266577Z",
      "totalSuspendedTime" : 0,
      "wasInterrupted" : false
    },
    "fileCount" : {
      "numberOfFileProviders" : 19,
      "numberOfScannedFiles" : 235909,
      "numberOfFilesIndexedByInfrastructureExtensionsDuringScan" : 0,
      "numberOfFilesScheduledForIndexingAfterScan" : 226861,
      "numberOfFilesIndexedByInfrastructureExtensionsDuringIndexingStage" : 0,
      "numberOfFilesIndexedWithLoadingContent" : 226861
    },
    "totalStatsPerFileType" : [ {
      "fileType" : "CLASS",
      "partOfTotalProcessingTime" : {
        "part" : 238123703382,
        "total" : 608864159737
      },
      "partOfTotalContentLoadingTime" : {
        "part" : 24375660929,
        "total" : 58726895686
      },
      "totalNumberOfFiles" : 146044,
      "totalFilesSize" : 560812067,
      "indexingSpeed" : {
        "totalBytes" : 560812067,
        "totalTime" : 238123703382
      },
      "biggestContributors" : [ {
        "providerName" : "Library Gradle: com.jetbrains:ideaIC:2022.2",
        "numberOfFiles" : 116860,
        "totalFilesSize" : 425167591,
        "partOfTotalProcessingTimeOfThisFileType" : {
          "part" : 197340856432,
          "total" : 238123703382
        }
      }, {
        "providerName" : "JDK openjdk-21",
        "numberOfFiles" : 27856,
        "totalFilesSize" : 131661939,
        "partOfTotalProcessingTimeOfThisFileType" : {
          "part" : 36124468946,
          "total" : 238123703382
        }
      }, {
        "providerName" : "Library Gradle: org.junit.platform:junit-platform-engine:1.9.3",
        "numberOfFiles" : 127,
        "totalFilesSize" : 404728,
        "partOfTotalProcessingTimeOfThisFileType" : {
          "part" : 1402125079,
          "total" : 238123703382
        }
      }, {
        "providerName" : "Library Gradle: junit:junit:4.13.2",
        "numberOfFiles" : 350,
        "totalFilesSize" : 716717,
        "partOfTotalProcessingTimeOfThisFileType" : {
          "part" : 1037988732,
          "total" : 238123703382
        }
      }, {
        "providerName" : "Library Gradle: org.junit.jupiter:junit-jupiter-api:5.9.3",
        "numberOfFiles" : 179,
        "totalFilesSize" : 420440,
        "partOfTotalProcessingTimeOfThisFileType" : {
          "part" : 805806110,
          "total" : 238123703382
        }
      }, {
        "providerName" : "Library Gradle: org.junit.jupiter:junit-jupiter-params:5.9.3",
        "numberOfFiles" : 343,
        "totalFilesSize" : 1318519,
        "partOfTotalProcessingTimeOfThisFileType" : {
          "part" : 683648839,
          "total" : 238123703382
        }
      }, {
        "providerName" : "Library Gradle: org.jetbrains:annotations:24.0.0",
        "numberOfFiles" : 60,
        "totalFilesSize" : 33574,
        "partOfTotalProcessingTimeOfThisFileType" : {
          "part" : 232047089,
          "total" : 238123703382
        }
      }, {
        "providerName" : "Library Gradle: org.hamcrest:hamcrest-core:1.3",
        "numberOfFiles" : 45,
        "totalFilesSize" : 93873,
        "partOfTotalProcessingTimeOfThisFileType" : {
          "part" : 216184858,
          "total" : 238123703382
        }
      }, {
        "providerName" : "Library Gradle: org.junit.jupiter:junit-jupiter-engine:5.9.3",
        "numberOfFiles" : 134,
        "totalFilesSize" : 621976,
        "partOfTotalProcessingTimeOfThisFileType" : {
          "part" : 157665887,
          "total" : 238123703382
        }
      }, {
        "providerName" : "Library Gradle: org.junit.platform:junit-platform-commons:1.9.3",
        "numberOfFiles" : 45,
        "totalFilesSize" : 226880,
        "partOfTotalProcessingTimeOfThisFileType" : {
          "part" : 59084380,
          "total" : 238123703382
        }
      } ]
    }, {
      "fileType" : "JAVA",
      "partOfTotalProcessingTime" : {
        "part" : 212774217391,
        "total" : 608864159737
      },
      "partOfTotalContentLoadingTime" : {
        "part" : 25617700566,
        "total" : 58726895686
      },
      "totalNumberOfFiles" : 60089,
      "totalFilesSize" : 470635410,
      "indexingSpeed" : {
        "totalBytes" : 470635410,
        "totalTime" : 212774217391
      },
      "biggestContributors" : [ {
        "providerName" : "Library Gradle: com.jetbrains:ideaIC:2022.2",
        "numberOfFiles" : 43787,
        "totalFilesSize" : 252785377,
        "partOfTotalProcessingTimeOfThisFileType" : {
          "part" : 123738012468,
          "total" : 212774217391
        }
      }, {
        "providerName" : "JDK openjdk-21",
        "numberOfFiles" : 15529,
        "totalFilesSize" : 215149747,
        "partOfTotalProcessingTimeOfThisFileType" : {
          "part" : 84886785689,
          "total" : 212774217391
        }
      }, {
        "providerName" : "Library Gradle: org.junit.platform:junit-platform-engine:1.9.3",
        "numberOfFiles" : 95,
        "totalFilesSize" : 364206,
        "partOfTotalProcessingTimeOfThisFileType" : {
          "part" : 1289401822,
          "total" : 212774217391
        }
      }, {
        "providerName" : "Library Gradle: junit:junit:4.13.2",
        "numberOfFiles" : 219,
        "totalFilesSize" : 666028,
        "partOfTotalProcessingTimeOfThisFileType" : {
          "part" : 929732880,
          "total" : 212774217391
        }
      }, {
        "providerName" : "Library Gradle: org.junit.jupiter:junit-jupiter-api:5.9.3",
        "numberOfFiles" : 147,
        "totalFilesSize" : 624845,
        "partOfTotalProcessingTimeOfThisFileType" : {
          "part" : 812599114,
          "total" : 212774217391
        }
      }, {
        "providerName" : "Library Gradle: org.jetbrains:annotations:24.0.0",
        "numberOfFiles" : 31,
        "totalFilesSize" : 75354,
        "partOfTotalProcessingTimeOfThisFileType" : {
          "part" : 251635461,
          "total" : 212774217391
        }
      }, {
        "providerName" : "Library Gradle: org.junit.jupiter:junit-jupiter-engine:5.9.3",
        "numberOfFiles" : 101,
        "totalFilesSize" : 340878,
        "partOfTotalProcessingTimeOfThisFileType" : {
          "part" : 222415584,
          "total" : 212774217391
        }
      }, {
        "providerName" : "Library Gradle: org.hamcrest:hamcrest-core:1.3",
        "numberOfFiles" : 38,
        "totalFilesSize" : 97196,
        "partOfTotalProcessingTimeOfThisFileType" : {
          "part" : 163852525,
          "total" : 212774217391
        }
      }, {
        "providerName" : "Library Gradle: org.junit.jupiter:junit-jupiter-params:5.9.3",
        "numberOfFiles" : 51,
        "totalFilesSize" : 168135,
        "partOfTotalProcessingTimeOfThisFileType" : {
          "part" : 156045982,
          "total" : 212774217391
        }
      }, {
        "providerName" : "Module 'DiffVerificate.main' (main)",
        "numberOfFiles" : 8,
        "totalFilesSize" : 27153,
        "partOfTotalProcessingTimeOfThisFileType" : {
          "part" : 142523019,
          "total" : 212774217391
        }
      } ]
    }, {
      "fileType" : "Kotlin",
      "partOfTotalProcessingTime" : {
        "part" : 122320555061,
        "total" : 608864159737
      },
      "partOfTotalContentLoadingTime" : {
        "part" : 7061406011,
        "total" : 58726895686
      },
      "totalNumberOfFiles" : 15633,
      "totalFilesSize" : 64892707,
      "indexingSpeed" : {
        "totalBytes" : 64892707,
        "totalTime" : 122320555061
      },
      "biggestContributors" : [ {
        "providerName" : "Library Gradle: com.jetbrains:ideaIC:2022.2",
        "numberOfFiles" : 15631,
        "totalFilesSize" : 64883317,
        "partOfTotalProcessingTimeOfThisFileType" : {
          "part" : 122188105273,
          "total" : 122320555061
        }
      }, {
        "providerName" : "Library Gradle: org.junit.jupiter:junit-jupiter-api:5.9.3",
        "numberOfFiles" : 1,
        "totalFilesSize" : 8366,
        "partOfTotalProcessingTimeOfThisFileType" : {
          "part" : 124208021,
          "total" : 122320555061
        }
      }, {
        "providerName" : "Library Gradle: org.junit.jupiter:junit-jupiter-params:5.9.3",
        "numberOfFiles" : 1,
        "totalFilesSize" : 1024,
        "partOfTotalProcessingTimeOfThisFileType" : {
          "part" : 8241767,
          "total" : 122320555061
        }
      } ]
    }, {
      "fileType" : "PLAIN_TEXT",
      "partOfTotalProcessingTime" : {
        "part" : 8515269396,
        "total" : 608864159737
      },
      "partOfTotalContentLoadingTime" : {
        "part" : 121862853,
        "total" : 58726895686
      },
      "totalNumberOfFiles" : 574,
      "totalFilesSize" : 6565075,
      "indexingSpeed" : {
        "totalBytes" : 6565075,
        "totalTime" : 8515269396
      },
      "biggestContributors" : [ {
        "providerName" : "Library Gradle: com.jetbrains:ideaIC:2022.2",
        "numberOfFiles" : 511,
        "totalFilesSize" : 6222979,
        "partOfTotalProcessingTimeOfThisFileType" : {
          "part" : 8237393360,
          "total" : 8515269396
        }
      }, {
        "providerName" : "JDK openjdk-21",
        "numberOfFiles" : 55,
        "totalFilesSize" : 284849,
        "partOfTotalProcessingTimeOfThisFileType" : {
          "part" : 229560171,
          "total" : 8515269396
        }
      }, {
        "providerName" : "Library Gradle: junit:junit:4.13.2",
        "numberOfFiles" : 3,
        "totalFilesSize" : 23036,
        "partOfTotalProcessingTimeOfThisFileType" : {
          "part" : 20739522,
          "total" : 8515269396
        }
      }, {
        "providerName" : "Library Gradle: org.apiguardian:apiguardian-api:1.1.2",
        "numberOfFiles" : 2,
        "totalFilesSize" : 22714,
        "partOfTotalProcessingTimeOfThisFileType" : {
          "part" : 12358866,
          "total" : 8515269396
        }
      }, {
        "providerName" : "Indexable set contributor 'com.intellij.javaee.ExternalResourcesRootsProvider@70ea837f' (non-project)",
        "numberOfFiles" : 2,
        "totalFilesSize" : 9988,
        "partOfTotalProcessingTimeOfThisFileType" : {
          "part" : 8276255,
          "total" : 8515269396
        }
      }, {
        "providerName" : "Library Gradle: org.hamcrest:hamcrest-core:1.3",
        "numberOfFiles" : 1,
        "totalFilesSize" : 1509,
        "partOfTotalProcessingTimeOfThisFileType" : {
          "part" : 6941222,
          "total" : 8515269396
        }
      } ]
    }, {
      "fileType" : "XML",
      "partOfTotalProcessingTime" : {
        "part" : 5761845296,
        "total" : 608864159737
      },
      "partOfTotalContentLoadingTime" : {
        "part" : 238105570,
        "total" : 58726895686
      },
      "totalNumberOfFiles" : 233,
      "totalFilesSize" : 5248573,
      "indexingSpeed" : {
        "totalBytes" : 5248573,
        "totalTime" : 5761845296
      },
      "biggestContributors" : [ {
        "providerName" : "Library Gradle: com.jetbrains:ideaIC:2022.2",
        "numberOfFiles" : 205,
        "totalFilesSize" : 4077588,
        "partOfTotalProcessingTimeOfThisFileType" : {
          "part" : 4508841587,
          "total" : 5761845296
        }
      }, {
        "providerName" : "Indexable set contributor 'com.intellij.javaee.ExternalResourcesRootsProvider@70ea837f' (non-project)",
        "numberOfFiles" : 24,
        "totalFilesSize" : 1118331,
        "partOfTotalProcessingTimeOfThisFileType" : {
          "part" : 1189993335,
          "total" : 5761845296
        }
      }, {
        "providerName" : "Module 'DiffVerificate.main' (main)",
        "numberOfFiles" : 1,
        "totalFilesSize" : 3857,
        "partOfTotalProcessingTimeOfThisFileType" : {
          "part" : 29306996,
          "total" : 5761845296
        }
      }, {
        "providerName" : "JDK openjdk-21",
        "numberOfFiles" : 2,
        "totalFilesSize" : 47677,
        "partOfTotalProcessingTimeOfThisFileType" : {
          "part" : 25531596,
          "total" : 5761845296
        }
      }, {
        "providerName" : "Module 'DiffVerificate' (DiffVerificate)",
        "numberOfFiles" : 1,
        "totalFilesSize" : 1120,
        "partOfTotalProcessingTimeOfThisFileType" : {
          "part" : 8171782,
          "total" : 5761845296
        }
      } ]
    }, {
      "fileType" : "SVG",
      "partOfTotalProcessingTime" : {
        "part" : 5073501131,
        "total" : 608864159737
      },
      "partOfTotalContentLoadingTime" : {
        "part" : 603646281,
        "total" : 58726895686
      },
      "totalNumberOfFiles" : 2760,
      "totalFilesSize" : 2993264,
      "indexingSpeed" : {
        "totalBytes" : 2993264,
        "totalTime" : 5073501131
      },
      "biggestContributors" : [ {
        "providerName" : "Library Gradle: com.jetbrains:ideaIC:2022.2",
        "numberOfFiles" : 2756,
        "totalFilesSize" : 2986962,
        "partOfTotalProcessingTimeOfThisFileType" : {
          "part" : 5063474254,
          "total" : 5073501131
        }
      }, {
        "providerName" : "JDK openjdk-21",
        "numberOfFiles" : 3,
        "totalFilesSize" : 5481,
        "partOfTotalProcessingTimeOfThisFileType" : {
          "part" : 6050936,
          "total" : 5073501131
        }
      }, {
        "providerName" : "Module 'DiffVerificate.main' (main)",
        "numberOfFiles" : 1,
        "totalFilesSize" : 821,
        "partOfTotalProcessingTimeOfThisFileType" : {
          "part" : 3975941,
          "total" : 5073501131
        }
      } ]
    }, {
      "fileType" : "JSON",
      "partOfTotalProcessingTime" : {
        "part" : 4302407215,
        "total" : 608864159737
      },
      "partOfTotalContentLoadingTime" : {
        "part" : 150125423,
        "total" : 58726895686
      },
      "totalNumberOfFiles" : 30,
      "totalFilesSize" : 10818160,
      "indexingSpeed" : {
        "totalBytes" : 10818160,
        "totalTime" : 4302407215
      },
      "biggestContributors" : [ {
        "providerName" : "Library Gradle: com.jetbrains:ideaIC:2022.2",
        "numberOfFiles" : 28,
        "totalFilesSize" : 10541941,
        "partOfTotalProcessingTimeOfThisFileType" : {
          "part" : 4055265038,
          "total" : 4302407215
        }
      }, {
        "providerName" : "Indexable set contributor 'com.intellij.javaee.ExternalResourcesRootsProvider@70ea837f' (non-project)",
        "numberOfFiles" : 1,
        "totalFilesSize" : 272615,
        "partOfTotalProcessingTimeOfThisFileType" : {
          "part" : 243796512,
          "total" : 4302407215
        }
      }, {
        "providerName" : "Indexable set contributor 'Scratches & Consoles' (non-project)",
        "numberOfFiles" : 1,
        "totalFilesSize" : 3604,
        "partOfTotalProcessingTimeOfThisFileType" : {
          "part" : 3345665,
          "total" : 4302407215
        }
      } ]
    }, {
      "fileType" : "Properties",
      "partOfTotalProcessingTime" : {
        "part" : 3153987670,
        "total" : 608864159737
      },
      "partOfTotalContentLoadingTime" : {
        "part" : 149164402,
        "total" : 58726895686
      },
      "totalNumberOfFiles" : 533,
      "totalFilesSize" : 3556763,
      "indexingSpeed" : {
        "totalBytes" : 3556763,
        "totalTime" : 3153987670
      },
      "biggestContributors" : [ {
        "providerName" : "Library Gradle: com.jetbrains:ideaIC:2022.2",
        "numberOfFiles" : 422,
        "totalFilesSize" : 2329015,
        "partOfTotalProcessingTimeOfThisFileType" : {
          "part" : 2450973874,
          "total" : 3153987670
        }
      }, {
        "providerName" : "JDK openjdk-21",
        "numberOfFiles" : 109,
        "totalFilesSize" : 1227152,
        "partOfTotalProcessingTimeOfThisFileType" : {
          "part" : 661677026,
          "total" : 3153987670
        }
      }, {
        "providerName" : "Module 'DiffVerificate' (DiffVerificate)",
        "numberOfFiles" : 2,
        "totalFilesSize" : 596,
        "partOfTotalProcessingTimeOfThisFileType" : {
          "part" : 41336770,
          "total" : 3153987670
        }
      } ]
    }, {
      "fileType" : "HTML",
      "partOfTotalProcessingTime" : {
        "part" : 3092492801,
        "total" : 608864159737
      },
      "partOfTotalContentLoadingTime" : {
        "part" : 172509041,
        "total" : 58726895686
      },
      "totalNumberOfFiles" : 378,
      "totalFilesSize" : 917886,
      "indexingSpeed" : {
        "totalBytes" : 917886,
        "totalTime" : 3092492801
      },
      "biggestContributors" : [ {
        "providerName" : "Library Gradle: com.jetbrains:ideaIC:2022.2",
        "numberOfFiles" : 376,
        "totalFilesSize" : 917530,
        "partOfTotalProcessingTimeOfThisFileType" : {
          "part" : 3074512168,
          "total" : 3092492801
        }
      }, {
        "providerName" : "Library Gradle: org.hamcrest:hamcrest-core:1.3",
        "numberOfFiles" : 2,
        "totalFilesSize" : 356,
        "partOfTotalProcessingTimeOfThisFileType" : {
          "part" : 17980633,
          "total" : 3092492801
        }
      } ]
    }, {
      "fileType" : "Groovy",
      "partOfTotalProcessingTime" : {
        "part" : 2041012764,
        "total" : 608864159737
      },
      "partOfTotalContentLoadingTime" : {
        "part" : 29762755,
        "total" : 58726895686
      },
      "totalNumberOfFiles" : 80,
      "totalFilesSize" : 214518,
      "indexingSpeed" : {
        "totalBytes" : 214518,
        "totalTime" : 2041012764
      },
      "biggestContributors" : [ {
        "providerName" : "Library Gradle: com.jetbrains:ideaIC:2022.2",
        "numberOfFiles" : 80,
        "totalFilesSize" : 214518,
        "partOfTotalProcessingTimeOfThisFileType" : {
          "part" : 2041012764,
          "total" : 2041012764
        }
      } ]
    }, {
      "fileType" : "DTD",
      "partOfTotalProcessingTime" : {
        "part" : 995436449,
        "total" : 608864159737
      },
      "partOfTotalContentLoadingTime" : {
        "part" : 69830949,
        "total" : 58726895686
      },
      "totalNumberOfFiles" : 128,
      "totalFilesSize" : 1819500,
      "indexingSpeed" : {
        "totalBytes" : 1819500,
        "totalTime" : 995436449
      },
      "biggestContributors" : [ {
        "providerName" : "Indexable set contributor 'com.intellij.javaee.ExternalResourcesRootsProvider@70ea837f' (non-project)",
        "numberOfFiles" : 64,
        "totalFilesSize" : 812613,
        "partOfTotalProcessingTimeOfThisFileType" : {
          "part" : 520753121,
          "total" : 995436449
        }
      }, {
        "providerName" : "Library Gradle: com.jetbrains:ideaIC:2022.2",
        "numberOfFiles" : 63,
        "totalFilesSize" : 1003995,
        "partOfTotalProcessingTimeOfThisFileType" : {
          "part" : 471798741,
          "total" : 995436449
        }
      }, {
        "providerName" : "JDK openjdk-21",
        "numberOfFiles" : 1,
        "totalFilesSize" : 2892,
        "partOfTotalProcessingTimeOfThisFileType" : {
          "part" : 2884587,
          "total" : 995436449
        }
      } ]
    }, {
      "fileType" : "Markdown",
      "partOfTotalProcessingTime" : {
        "part" : 888999081,
        "total" : 608864159737
      },
      "partOfTotalContentLoadingTime" : {
        "part" : 14959266,
        "total" : 58726895686
      },
      "totalNumberOfFiles" : 30,
      "totalFilesSize" : 195432,
      "indexingSpeed" : {
        "totalBytes" : 195432,
        "totalTime" : 888999081
      },
      "biggestContributors" : [ {
        "providerName" : "Library Gradle: org.junit.platform:junit-platform-engine:1.9.3",
        "numberOfFiles" : 4,
        "totalFilesSize" : 29102,
        "partOfTotalProcessingTimeOfThisFileType" : {
          "part" : 457317895,
          "total" : 888999081
        }
      }, {
        "providerName" : "Library Gradle: org.junit.jupiter:junit-jupiter-api:5.9.3",
        "numberOfFiles" : 4,
        "totalFilesSize" : 29102,
        "partOfTotalProcessingTimeOfThisFileType" : {
          "part" : 118125250,
          "total" : 888999081
        }
      }, {
        "providerName" : "Library Gradle: org.junit.jupiter:junit-jupiter-params:5.9.3",
        "numberOfFiles" : 5,
        "totalFilesSize" : 38405,
        "partOfTotalProcessingTimeOfThisFileType" : {
          "part" : 109488743,
          "total" : 888999081
        }
      }, {
        "providerName" : "Library Gradle: com.jetbrains:ideaIC:2022.2",
        "numberOfFiles" : 5,
        "totalFilesSize" : 11517,
        "partOfTotalProcessingTimeOfThisFileType" : {
          "part" : 79435414,
          "total" : 888999081
        }
      }, {
        "providerName" : "Library Gradle: org.junit.jupiter:junit-jupiter-engine:5.9.3",
        "numberOfFiles" : 4,
        "totalFilesSize" : 29102,
        "partOfTotalProcessingTimeOfThisFileType" : {
          "part" : 45061855,
          "total" : 888999081
        }
      }, {
        "providerName" : "Library Gradle: org.junit.vintage:junit-vintage-engine:5.9.3",
        "numberOfFiles" : 4,
        "totalFilesSize" : 29102,
        "partOfTotalProcessingTimeOfThisFileType" : {
          "part" : 44627435,
          "total" : 888999081
        }
      }, {
        "providerName" : "Library Gradle: org.junit.platform:junit-platform-commons:1.9.3",
        "numberOfFiles" : 4,
        "totalFilesSize" : 29102,
        "partOfTotalProcessingTimeOfThisFileType" : {
          "part" : 34942489,
          "total" : 888999081
        }
      } ]
    }, {
      "fileType" : "RNG Compact",
      "partOfTotalProcessingTime" : {
        "part" : 418860441,
        "total" : 608864159737
      },
      "partOfTotalContentLoadingTime" : {
        "part" : 49894029,
        "total" : 58726895686
      },
      "totalNumberOfFiles" : 125,
      "totalFilesSize" : 472596,
      "indexingSpeed" : {
        "totalBytes" : 472596,
        "totalTime" : 418860441
      },
      "biggestContributors" : [ {
        "providerName" : "Indexable set contributor 'com.intellij.javaee.ExternalResourcesRootsProvider@70ea837f' (non-project)",
        "numberOfFiles" : 124,
        "totalFilesSize" : 468783,
        "partOfTotalProcessingTimeOfThisFileType" : {
          "part" : 417042578,
          "total" : 418860441
        }
      }, {
        "providerName" : "Library Gradle: com.jetbrains:ideaIC:2022.2",
        "numberOfFiles" : 1,
        "totalFilesSize" : 3813,
        "partOfTotalProcessingTimeOfThisFileType" : {
          "part" : 1817863,
          "total" : 418860441
        }
      } ]
    }, {
      "fileType" : "JavaScript",
      "partOfTotalProcessingTime" : {
        "part" : 307351529,
        "total" : 608864159737
      },
      "partOfTotalContentLoadingTime" : {
        "part" : 4203943,
        "total" : 58726895686
      },
      "totalNumberOfFiles" : 9,
      "totalFilesSize" : 531828,
      "indexingSpeed" : {
        "totalBytes" : 531828,
        "totalTime" : 307351529
      },
      "biggestContributors" : [ {
        "providerName" : "JDK openjdk-21",
        "numberOfFiles" : 7,
        "totalFilesSize" : 529851,
        "partOfTotalProcessingTimeOfThisFileType" : {
          "part" : 301487296,
          "total" : 307351529
        }
      }, {
        "providerName" : "Library Gradle: com.jetbrains:ideaIC:2022.2",
        "numberOfFiles" : 2,
        "totalFilesSize" : 1977,
        "partOfTotalProcessingTimeOfThisFileType" : {
          "part" : 5864233,
          "total" : 307351529
        }
      } ]
    }, {
      "fileType" : "Gradle",
      "partOfTotalProcessingTime" : {
        "part" : 211277208,
        "total" : 608864159737
      },
      "partOfTotalContentLoadingTime" : {
        "part" : 329224,
        "total" : 58726895686
      },
      "totalNumberOfFiles" : 2,
      "totalFilesSize" : 1551,
      "indexingSpeed" : {
        "totalBytes" : 1551,
        "totalTime" : 211277208
      },
      "biggestContributors" : [ {
        "providerName" : "Module 'DiffVerificate' (DiffVerificate)",
        "numberOfFiles" : 2,
        "totalFilesSize" : 1551,
        "partOfTotalProcessingTimeOfThisFileType" : {
          "part" : 211277208,
          "total" : 211277208
        }
      } ]
    }, {
      "fileType" : "kotlin_builtins",
      "partOfTotalProcessingTime" : {
        "part" : 167531924,
        "total" : 608864159737
      },
      "partOfTotalContentLoadingTime" : {
        "part" : 1014782,
        "total" : 58726895686
      },
      "totalNumberOfFiles" : 7,
      "totalFilesSize" : 24464,
      "indexingSpeed" : {
        "totalBytes" : 24464,
        "totalTime" : 167531924
      },
      "biggestContributors" : [ {
        "providerName" : "Library Gradle: com.jetbrains:ideaIC:2022.2",
        "numberOfFiles" : 7,
        "totalFilesSize" : 24464,
        "partOfTotalProcessingTimeOfThisFileType" : {
          "part" : 167531924,
          "total" : 167531924
        }
      } ]
    }, {
      "fileType" : "Manifest",
      "partOfTotalProcessingTime" : {
        "part" : 133904246,
        "total" : 608864159737
      },
      "partOfTotalContentLoadingTime" : {
        "part" : 23097135,
        "total" : 58726895686
      },
      "totalNumberOfFiles" : 48,
      "totalFilesSize" : 30320,
      "indexingSpeed" : {
        "totalBytes" : 30320,
        "totalTime" : 133904246
      },
      "biggestContributors" : [ {
        "providerName" : "Library Gradle: com.jetbrains:ideaIC:2022.2",
        "numberOfFiles" : 26,
        "totalFilesSize" : 12113,
        "partOfTotalProcessingTimeOfThisFileType" : {
          "part" : 46025311,
          "total" : 133904246
        }
      }, {
        "providerName" : "Library Gradle: org.junit.platform:junit-platform-engine:1.9.3",
        "numberOfFiles" : 2,
        "totalFilesSize" : 2400,
        "partOfTotalProcessingTimeOfThisFileType" : {
          "part" : 42717155,
          "total" : 133904246
        }
      }, {
        "providerName" : "Library Gradle: org.junit.jupiter:junit-jupiter-api:5.9.3",
        "numberOfFiles" : 2,
        "totalFilesSize" : 2611,
        "partOfTotalProcessingTimeOfThisFileType" : {
          "part" : 9177650,
          "total" : 133904246
        }
      }, {
        "providerName" : "Library Gradle: junit:junit:4.13.2",
        "numberOfFiles" : 2,
        "totalFilesSize" : 450,
        "partOfTotalProcessingTimeOfThisFileType" : {
          "part" : 8178970,
          "total" : 133904246
        }
      }, {
        "providerName" : "Library Gradle: org.jetbrains:annotations:24.0.0",
        "numberOfFiles" : 2,
        "totalFilesSize" : 71,
        "partOfTotalProcessingTimeOfThisFileType" : {
          "part" : 4476985,
          "total" : 133904246
        }
      }, {
        "providerName" : "Library Gradle: org.opentest4j:opentest4j:1.2.0",
        "numberOfFiles" : 2,
        "totalFilesSize" : 815,
        "partOfTotalProcessingTimeOfThisFileType" : {
          "part" : 4201236,
          "total" : 133904246
        }
      }, {
        "providerName" : "Library Gradle: org.junit.jupiter:junit-jupiter-engine:5.9.3",
        "numberOfFiles" : 2,
        "totalFilesSize" : 3833,
        "partOfTotalProcessingTimeOfThisFileType" : {
          "part" : 4162624,
          "total" : 133904246
        }
      }, {
        "providerName" : "Library Gradle: org.hamcrest:hamcrest-core:1.3",
        "numberOfFiles" : 2,
        "totalFilesSize" : 514,
        "partOfTotalProcessingTimeOfThisFileType" : {
          "part" : 3605541,
          "total" : 133904246
        }
      }, {
        "providerName" : "Library Gradle: org.junit.jupiter:junit-jupiter-params:5.9.3",
        "numberOfFiles" : 2,
        "totalFilesSize" : 2074,
        "partOfTotalProcessingTimeOfThisFileType" : {
          "part" : 3574582,
          "total" : 133904246
        }
      }, {
        "providerName" : "Library Gradle: org.apiguardian:apiguardian-api:1.1.2",
        "numberOfFiles" : 2,
        "totalFilesSize" : 887,
        "partOfTotalProcessingTimeOfThisFileType" : {
          "part" : 2728737,
          "total" : 133904246
        }
      } ]
    }, {
      "fileType" : "kotlin_module",
      "partOfTotalProcessingTime" : {
        "part" : 114972102,
        "total" : 608864159737
      },
      "partOfTotalContentLoadingTime" : {
        "part" : 6363585,
        "total" : 58726895686
      },
      "totalNumberOfFiles" : 19,
      "totalFilesSize" : 4857,
      "indexingSpeed" : {
        "totalBytes" : 4857,
        "totalTime" : 114972102
      },
      "biggestContributors" : [ {
        "providerName" : "Library Gradle: org.junit.jupiter:junit-jupiter-api:5.9.3",
        "numberOfFiles" : 1,
        "totalFilesSize" : 59,
        "partOfTotalProcessingTimeOfThisFileType" : {
          "part" : 93126171,
          "total" : 114972102
        }
      }, {
        "providerName" : "Library Gradle: com.jetbrains:ideaIC:2022.2",
        "numberOfFiles" : 17,
        "totalFilesSize" : 4718,
        "partOfTotalProcessingTimeOfThisFileType" : {
          "part" : 16312259,
          "total" : 114972102
        }
      }, {
        "providerName" : "Library Gradle: org.junit.jupiter:junit-jupiter-params:5.9.3",
        "numberOfFiles" : 1,
        "totalFilesSize" : 80,
        "partOfTotalProcessingTimeOfThisFileType" : {
          "part" : 5533672,
          "total" : 114972102
        }
      } ]
    }, {
      "fileType" : "Dictionary",
      "partOfTotalProcessingTime" : {
        "part" : 103064618,
        "total" : 608864159737
      },
      "partOfTotalContentLoadingTime" : {
        "part" : 13390931,
        "total" : 58726895686
      },
      "totalNumberOfFiles" : 1,
      "totalFilesSize" : 1572753,
      "indexingSpeed" : {
        "totalBytes" : 1572753,
        "totalTime" : 103064618
      },
      "biggestContributors" : [ {
        "providerName" : "Library Gradle: com.jetbrains:ideaIC:2022.2",
        "numberOfFiles" : 1,
        "totalFilesSize" : 1572753,
        "partOfTotalProcessingTimeOfThisFileType" : {
          "part" : 103064618,
          "total" : 103064618
        }
      } ]
    }, {
      "fileType" : "SPI",
      "partOfTotalProcessingTime" : {
        "part" : 80516161,
        "total" : 608864159737
      },
      "partOfTotalContentLoadingTime" : {
        "part" : 10591167,
        "total" : 58726895686
      },
      "totalNumberOfFiles" : 72,
      "totalFilesSize" : 27227,
      "indexingSpeed" : {
        "totalBytes" : 27227,
        "totalTime" : 80516161
      },
      "biggestContributors" : [ {
        "providerName" : "Library Gradle: com.jetbrains:ideaIC:2022.2",
        "numberOfFiles" : 67,
        "totalFilesSize" : 27018,
        "partOfTotalProcessingTimeOfThisFileType" : {
          "part" : 77164401,
          "total" : 80516161
        }
      }, {
        "providerName" : "Library Gradle: org.junit.vintage:junit-vintage-engine:5.9.3",
        "numberOfFiles" : 2,
        "totalFilesSize" : 84,
        "partOfTotalProcessingTimeOfThisFileType" : {
          "part" : 1531123,
          "total" : 80516161
        }
      }, {
        "providerName" : "Library Gradle: org.junit.jupiter:junit-jupiter-engine:5.9.3",
        "numberOfFiles" : 2,
        "totalFilesSize" : 84,
        "partOfTotalProcessingTimeOfThisFileType" : {
          "part" : 1160526,
          "total" : 80516161
        }
      }, {
        "providerName" : "JDK openjdk-21",
        "numberOfFiles" : 1,
        "totalFilesSize" : 41,
        "partOfTotalProcessingTimeOfThisFileType" : {
          "part" : 660111,
          "total" : 80516161
        }
      } ]
    }, {
      "fileType" : "CSS",
      "partOfTotalProcessingTime" : {
        "part" : 79082236,
        "total" : 608864159737
      },
      "partOfTotalContentLoadingTime" : {
        "part" : 2614604,
        "total" : 58726895686
      },
      "totalNumberOfFiles" : 13,
      "totalFilesSize" : 80339,
      "indexingSpeed" : {
        "totalBytes" : 80339,
        "totalTime" : 79082236
      },
      "biggestContributors" : [ {
        "providerName" : "Library Gradle: com.jetbrains:ideaIC:2022.2",
        "numberOfFiles" : 8,
        "totalFilesSize" : 34648,
        "partOfTotalProcessingTimeOfThisFileType" : {
          "part" : 52621361,
          "total" : 79082236
        }
      }, {
        "providerName" : "JDK openjdk-21",
        "numberOfFiles" : 4,
        "totalFilesSize" : 40153,
        "partOfTotalProcessingTimeOfThisFileType" : {
          "part" : 21523976,
          "total" : 79082236
        }
      }, {
        "providerName" : "Indexable set contributor 'com.intellij.javaee.ExternalResourcesRootsProvider@70ea837f' (non-project)",
        "numberOfFiles" : 1,
        "totalFilesSize" : 5538,
        "partOfTotalProcessingTimeOfThisFileType" : {
          "part" : 4936899,
          "total" : 79082236
        }
      } ]
    }, {
      "fileType" : "textmate",
      "partOfTotalProcessingTime" : {
        "part" : 78511176,
        "total" : 608864159737
      },
      "partOfTotalContentLoadingTime" : {
        "part" : 4071075,
        "total" : 58726895686
      },
      "totalNumberOfFiles" : 21,
      "totalFilesSize" : 97878,
      "indexingSpeed" : {
        "totalBytes" : 97878,
        "totalTime" : 78511176
      },
      "biggestContributors" : [ {
        "providerName" : "Library Gradle: com.jetbrains:ideaIC:2022.2",
        "numberOfFiles" : 17,
        "totalFilesSize" : 77532,
        "partOfTotalProcessingTimeOfThisFileType" : {
          "part" : 53828717,
          "total" : 78511176
        }
      }, {
        "providerName" : "Indexable set contributor 'com.intellij.javaee.ExternalResourcesRootsProvider@70ea837f' (non-project)",
        "numberOfFiles" : 3,
        "totalFilesSize" : 17583,
        "partOfTotalProcessingTimeOfThisFileType" : {
          "part" : 13294095,
          "total" : 78511176
        }
      }, {
        "providerName" : "Module 'DiffVerificate' (DiffVerificate)",
        "numberOfFiles" : 1,
        "totalFilesSize" : 2763,
        "partOfTotalProcessingTimeOfThisFileType" : {
          "part" : 11388364,
          "total" : 78511176
        }
      } ]
    }, {
      "fileType" : "Shell Script",
      "partOfTotalProcessingTime" : {
        "part" : 62923015,
        "total" : 608864159737
      },
      "partOfTotalContentLoadingTime" : {
        "part" : 1835994,
        "total" : 58726895686
      },
      "totalNumberOfFiles" : 13,
      "totalFilesSize" : 12620,
      "indexingSpeed" : {
        "totalBytes" : 12620,
        "totalTime" : 62923015
      },
      "biggestContributors" : [ {
        "providerName" : "Module 'DiffVerificate' (DiffVerificate)",
        "numberOfFiles" : 1,
        "totalFilesSize" : 8070,
        "partOfTotalProcessingTimeOfThisFileType" : {
          "part" : 27454352,
          "total" : 62923015
        }
      }, {
        "providerName" : "JDK openjdk-21",
        "numberOfFiles" : 6,
        "totalFilesSize" : 1361,
        "partOfTotalProcessingTimeOfThisFileType" : {
          "part" : 15791054,
          "total" : 62923015
        }
      }, {
        "providerName" : "Library Gradle: com.jetbrains:ideaIC:2022.2",
        "numberOfFiles" : 5,
        "totalFilesSize" : 2002,
        "partOfTotalProcessingTimeOfThisFileType" : {
          "part" : 14602430,
          "total" : 62923015
        }
      }, {
        "providerName" : "Indexable set contributor 'com.intellij.javaee.ExternalResourcesRootsProvider@70ea837f' (non-project)",
        "numberOfFiles" : 1,
        "totalFilesSize" : 1187,
        "partOfTotalProcessingTimeOfThisFileType" : {
          "part" : 5075179,
          "total" : 62923015
        }
      } ]
    }, {
      "fileType" : "Shrinker Config File",
      "partOfTotalProcessingTime" : {
        "part" : 26786699,
        "total" : 608864159737
      },
      "partOfTotalContentLoadingTime" : {
        "part" : 1308009,
        "total" : 58726895686
      },
      "totalNumberOfFiles" : 6,
      "totalFilesSize" : 5957,
      "indexingSpeed" : {
        "totalBytes" : 5957,
        "totalTime" : 26786699
      },
      "biggestContributors" : [ {
        "providerName" : "Library Gradle: com.jetbrains:ideaIC:2022.2",
        "numberOfFiles" : 6,
        "totalFilesSize" : 5957,
        "partOfTotalProcessingTimeOfThisFileType" : {
          "part" : 26786699,
          "total" : 26786699
        }
      } ]
    }, {
      "fileType" : "XHTML",
      "partOfTotalProcessingTime" : {
        "part" : 11291613,
        "total" : 608864159737
      },
      "partOfTotalContentLoadingTime" : {
        "part" : 710281,
        "total" : 58726895686
      },
      "totalNumberOfFiles" : 1,
      "totalFilesSize" : 2908,
      "indexingSpeed" : {
        "totalBytes" : 2908,
        "totalTime" : 11291613
      },
      "biggestContributors" : [ {
        "providerName" : "Indexable set contributor 'com.intellij.javaee.ExternalResourcesRootsProvider@70ea837f' (non-project)",
        "numberOfFiles" : 1,
        "totalFilesSize" : 2908,
        "partOfTotalProcessingTimeOfThisFileType" : {
          "part" : 11291613,
          "total" : 11291613
        }
      } ]
    }, {
      "fileType" : "GUI_DESIGNER_FORM",
      "partOfTotalProcessingTime" : {
        "part" : 7390449,
        "total" : 608864159737
      },
      "partOfTotalContentLoadingTime" : {
        "part" : 453507,
        "total" : 58726895686
      },
      "totalNumberOfFiles" : 1,
      "totalFilesSize" : 8010,
      "indexingSpeed" : {
        "totalBytes" : 8010,
        "totalTime" : 7390449
      },
      "biggestContributors" : [ {
        "providerName" : "Library Gradle: com.jetbrains:ideaIC:2022.2",
        "numberOfFiles" : 1,
        "totalFilesSize" : 8010,
        "partOfTotalProcessingTimeOfThisFileType" : {
          "part" : 7390449,
          "total" : 7390449
        }
      } ]
    }, {
      "fileType" : "Perl",
      "partOfTotalProcessingTime" : {
        "part" : 5971670,
        "total" : 608864159737
      },
      "partOfTotalContentLoadingTime" : {
        "part" : 277193,
        "total" : 58726895686
      },
      "totalNumberOfFiles" : 1,
      "totalFilesSize" : 6523,
      "indexingSpeed" : {
        "totalBytes" : 6523,
        "totalTime" : 5971670
      },
      "biggestContributors" : [ {
        "providerName" : "Library Gradle: com.jetbrains:ideaIC:2022.2",
        "numberOfFiles" : 1,
        "totalFilesSize" : 6523,
        "partOfTotalProcessingTimeOfThisFileType" : {
          "part" : 5971670,
          "total" : 5971670
        }
      } ]
    }, {
      "fileType" : "PATCH",
      "partOfTotalProcessingTime" : {
        "part" : 4562487,
        "total" : 608864159737
      },
      "partOfTotalContentLoadingTime" : {
        "part" : 668340,
        "total" : 58726895686
      },
      "totalNumberOfFiles" : 8,
      "totalFilesSize" : 4449,
      "indexingSpeed" : {
        "totalBytes" : 4449,
        "totalTime" : 4562487
      },
      "biggestContributors" : [ {
        "providerName" : "Indexable set contributor 'com.intellij.javaee.ExternalResourcesRootsProvider@70ea837f' (non-project)",
        "numberOfFiles" : 8,
        "totalFilesSize" : 4449,
        "partOfTotalProcessingTimeOfThisFileType" : {
          "part" : 4562487,
          "total" : 4562487
        }
      } ]
    }, {
      "fileType" : "DGM",
      "partOfTotalProcessingTime" : {
        "part" : 3510035,
        "total" : 608864159737
      },
      "partOfTotalContentLoadingTime" : {
        "part" : 223196,
        "total" : 58726895686
      },
      "totalNumberOfFiles" : 1,
      "totalFilesSize" : 178,
      "indexingSpeed" : {
        "totalBytes" : 178,
        "totalTime" : 3510035
      },
      "biggestContributors" : [ {
        "providerName" : "Library Gradle: com.jetbrains:ideaIC:2022.2",
        "numberOfFiles" : 1,
        "totalFilesSize" : 178,
        "partOfTotalProcessingTimeOfThisFileType" : {
          "part" : 3510035,
          "total" : 3510035
        }
      } ]
    }, {
      "fileType" : "GitIgnore file",
      "partOfTotalProcessingTime" : {
        "part" : 3224491,
        "total" : 608864159737
      },
      "partOfTotalContentLoadingTime" : {
        "part" : 1114645,
        "total" : 58726895686
      },
      "totalNumberOfFiles" : 1,
      "totalFilesSize" : 539,
      "indexingSpeed" : {
        "totalBytes" : 539,
        "totalTime" : 3224491
      },
      "biggestContributors" : [ {
        "providerName" : "Module 'DiffVerificate' (DiffVerificate)",
        "numberOfFiles" : 1,
        "totalFilesSize" : 539,
        "partOfTotalProcessingTimeOfThisFileType" : {
          "part" : 3224491,
          "total" : 3224491
        }
      } ]
    } ],
    "totalStatsPerIndexer" : [ {
      "indexId" : "Stubs",
      "partOfTotalIndexingTime" : {
        "part" : 157820904778,
        "total" : 263651520961
      },
      "totalNumberOfFiles" : 162949,
      "totalNumberOfFilesIndexedByExtensions" : 0,
      "totalFilesSize" : 635891292,
      "indexingSpeed" : {
        "totalBytes" : 635891292,
        "totalTime" : 157820904778
      },
      "snapshotInputMappingStats" : {
        "totalRequests" : 0,
        "totalMisses" : 0,
        "totalHits" : 0
      }
    }, {
      "indexId" : "IdIndex",
      "partOfTotalIndexingTime" : {
        "part" : 56973358727,
        "total" : 263651520961
      },
      "totalNumberOfFiles" : 80782,
      "totalNumberOfFilesIndexedByExtensions" : 0,
      "totalFilesSize" : 569135762,
      "indexingSpeed" : {
        "totalBytes" : 569135762,
        "totalTime" : 56973358727
      },
      "snapshotInputMappingStats" : {
        "totalRequests" : 0,
        "totalMisses" : 0,
        "totalHits" : 0
      }
    }, {
      "indexId" : "Trigram.Index",
      "partOfTotalIndexingTime" : {
        "part" : 22571694467,
        "total" : 263651520961
      },
      "totalNumberOfFiles" : 77156,
      "totalNumberOfFilesIndexedByExtensions" : 0,
      "totalFilesSize" : 545416452,
      "indexingSpeed" : {
        "totalBytes" : 545416452,
        "totalTime" : 22571694467
      },
      "snapshotInputMappingStats" : {
        "totalRequests" : 0,
        "totalMisses" : 0,
        "totalHits" : 0
      }
    }, {
      "indexId" : "org.jetbrains.kotlin.idea.vfilefinder.KotlinPartialPackageNamesIndex",
      "partOfTotalIndexingTime" : {
        "part" : 19607077897,
        "total" : 263651520961
      },
      "totalNumberOfFiles" : 65698,
      "totalNumberOfFilesIndexedByExtensions" : 0,
      "totalFilesSize" : 274199247,
      "indexingSpeed" : {
        "totalBytes" : 274199247,
        "totalTime" : 19607077897
      },
      "snapshotInputMappingStats" : {
        "totalRequests" : 0,
        "totalMisses" : 0,
        "totalHits" : 0
      }
    }, {
      "indexId" : "bytecodeAnalysis",
      "partOfTotalIndexingTime" : {
        "part" : 3722574117,
        "total" : 263651520961
      },
      "totalNumberOfFiles" : 50081,
      "totalNumberOfFilesIndexedByExtensions" : 0,
      "totalFilesSize" : 209376314,
      "indexingSpeed" : {
        "totalBytes" : 209376314,
        "totalTime" : 3722574117
      },
      "snapshotInputMappingStats" : {
        "totalRequests" : 0,
        "totalMisses" : 0,
        "totalHits" : 0
      }
    }, {
      "indexId" : "org.jetbrains.kotlin.idea.versions.KotlinJvmMetadataVersionIndex",
      "partOfTotalIndexingTime" : {
        "part" : 766661486,
        "total" : 263651520961
      },
      "totalNumberOfFiles" : 50081,
      "totalNumberOfFilesIndexedByExtensions" : 0,
      "totalFilesSize" : 209376314,
      "indexingSpeed" : {
        "totalBytes" : 209376314,
        "totalTime" : 766661486
      },
      "snapshotInputMappingStats" : {
        "totalRequests" : 0,
        "totalMisses" : 0,
        "totalHits" : 0
      }
    }, {
      "indexId" : "org.jetbrains.kotlin.idea.vfilefinder.KotlinPackageSourcesMemberNamesIndex",
      "partOfTotalIndexingTime" : {
        "part" : 559602874,
        "total" : 263651520961
      },
      "totalNumberOfFiles" : 15617,
      "totalNumberOfFilesIndexedByExtensions" : 0,
      "totalFilesSize" : 64822933,
      "indexingSpeed" : {
        "totalBytes" : 64822933,
        "totalTime" : 559602874
      },
      "snapshotInputMappingStats" : {
        "totalRequests" : 0,
        "totalMisses" : 0,
        "totalHits" : 0
      }
    }, {
      "indexId" : "org.jetbrains.kotlin.idea.vfilefinder.KotlinClassFileIndex",
      "partOfTotalIndexingTime" : {
        "part" : 542086076,
        "total" : 263651520961
      },
      "totalNumberOfFiles" : 50081,
      "totalNumberOfFilesIndexedByExtensions" : 0,
      "totalFilesSize" : 209376314,
      "indexingSpeed" : {
        "totalBytes" : 209376314,
        "totalTime" : 542086076
      },
      "snapshotInputMappingStats" : {
        "totalRequests" : 0,
        "totalMisses" : 0,
        "totalHits" : 0
      }
    }, {
      "indexId" : "XmlNamespaces",
      "partOfTotalIndexingTime" : {
        "part" : 284910072,
        "total" : 263651520961
      },
      "totalNumberOfFiles" : 21,
      "totalNumberOfFilesIndexedByExtensions" : 0,
      "totalFilesSize" : 927785,
      "indexingSpeed" : {
        "totalBytes" : 927785,
        "totalTime" : 284910072
      },
      "snapshotInputMappingStats" : {
        "totalRequests" : 0,
        "totalMisses" : 0,
        "totalHits" : 0
      }
    }, {
      "indexId" : "XmlTagNames",
      "partOfTotalIndexingTime" : {
        "part" : 247554329,
        "total" : 263651520961
      },
      "totalNumberOfFiles" : 11,
      "totalNumberOfFilesIndexedByExtensions" : 0,
      "totalFilesSize" : 415206,
      "indexingSpeed" : {
        "totalBytes" : 415206,
        "totalTime" : 247554329
      },
      "snapshotInputMappingStats" : {
        "totalRequests" : 0,
        "totalMisses" : 0,
        "totalHits" : 0
      }
    }, {
      "indexId" : "SchemaTypeInheritance",
      "partOfTotalIndexingTime" : {
        "part" : 128806788,
        "total" : 263651520961
      },
      "totalNumberOfFiles" : 11,
      "totalNumberOfFilesIndexedByExtensions" : 0,
      "totalFilesSize" : 415206,
      "indexingSpeed" : {
        "totalBytes" : 415206,
        "totalTime" : 128806788
      },
      "snapshotInputMappingStats" : {
        "totalRequests" : 0,
        "totalMisses" : 0,
        "totalHits" : 0
      }
    }, {
      "indexId" : "org.jetbrains.kotlin.idea.vfilefinder.KotlinModuleMappingIndex",
      "partOfTotalIndexingTime" : {
        "part" : 89158581,
        "total" : 263651520961
      },
      "totalNumberOfFiles" : 19,
      "totalNumberOfFilesIndexedByExtensions" : 0,
      "totalFilesSize" : 4857,
      "indexingSpeed" : {
        "totalBytes" : 4857,
        "totalTime" : 89158581
      },
      "snapshotInputMappingStats" : {
        "totalRequests" : 0,
        "totalMisses" : 0,
        "totalHits" : 0
      }
    }, {
      "indexId" : "IdeaPluginRegistrationIndex",
      "partOfTotalIndexingTime" : {
        "part" : 61234827,
        "total" : 263651520961
      },
      "totalNumberOfFiles" : 53,
      "totalNumberOfFilesIndexedByExtensions" : 0,
      "totalFilesSize" : 1811154,
      "indexingSpeed" : {
        "totalBytes" : 1811154,
        "totalTime" : 61234827
      },
      "snapshotInputMappingStats" : {
        "totalRequests" : 0,
        "totalMisses" : 0,
        "totalHits" : 0
      }
    }, {
      "indexId" : "devkit.ExtensionPointIndex",
      "partOfTotalIndexingTime" : {
        "part" : 57021116,
        "total" : 263651520961
      },
      "totalNumberOfFiles" : 53,
      "totalNumberOfFilesIndexedByExtensions" : 0,
      "totalFilesSize" : 1811154,
      "indexingSpeed" : {
        "totalBytes" : 1811154,
        "totalTime" : 57021116
      },
      "snapshotInputMappingStats" : {
        "totalRequests" : 0,
        "totalMisses" : 0,
        "totalHits" : 0
      }
    }, {
      "indexId" : "devkit.ExtensionPointClassIndex",
      "partOfTotalIndexingTime" : {
        "part" : 38615797,
        "total" : 263651520961
      },
      "totalNumberOfFiles" : 53,
      "totalNumberOfFilesIndexedByExtensions" : 0,
      "totalFilesSize" : 1811154,
      "indexingSpeed" : {
        "totalBytes" : 1811154,
        "totalTime" : 38615797
      },
      "snapshotInputMappingStats" : {
        "totalRequests" : 0,
        "totalMisses" : 0,
        "totalHits" : 0
      }
    }, {
      "indexId" : "xmlProperties",
      "partOfTotalIndexingTime" : {
        "part" : 36772250,
        "total" : 263651520961
      },
      "totalNumberOfFiles" : 30,
      "totalNumberOfFilesIndexedByExtensions" : 0,
      "totalFilesSize" : 854986,
      "indexingSpeed" : {
        "totalBytes" : 854986,
        "totalTime" : 36772250
      },
      "snapshotInputMappingStats" : {
        "totalRequests" : 0,
        "totalMisses" : 0,
        "totalHits" : 0
      }
    }, {
      "indexId" : "DomFileIndex",
      "partOfTotalIndexingTime" : {
        "part" : 27170804,
        "total" : 263651520961
      },
      "totalNumberOfFiles" : 53,
      "totalNumberOfFilesIndexedByExtensions" : 0,
      "totalFilesSize" : 1811154,
      "indexingSpeed" : {
        "totalBytes" : 1811154,
        "totalTime" : 27170804
      },
      "snapshotInputMappingStats" : {
        "totalRequests" : 0,
        "totalMisses" : 0,
        "totalHits" : 0
      }
    }, {
      "indexId" : "java.fun.expression",
      "partOfTotalIndexingTime" : {
        "part" : 24379502,
        "total" : 263651520961
      },
      "totalNumberOfFiles" : 2,
      "totalNumberOfFilesIndexedByExtensions" : 0,
      "totalFilesSize" : 7445,
      "indexingSpeed" : {
        "totalBytes" : 7445,
        "totalTime" : 24379502
      },
      "snapshotInputMappingStats" : {
        "totalRequests" : 0,
        "totalMisses" : 0,
        "totalHits" : 0
      }
    }, {
      "indexId" : "PluginIdDependenciesIndex",
      "partOfTotalIndexingTime" : {
        "part" : 24188947,
        "total" : 263651520961
      },
      "totalNumberOfFiles" : 53,
      "totalNumberOfFilesIndexedByExtensions" : 0,
      "totalFilesSize" : 1811154,
      "indexingSpeed" : {
        "totalBytes" : 1811154,
        "totalTime" : 24188947
      },
      "snapshotInputMappingStats" : {
        "totalRequests" : 0,
        "totalMisses" : 0,
        "totalHits" : 0
      }
    }, {
      "indexId" : "PluginIdModuleIndex",
      "partOfTotalIndexingTime" : {
        "part" : 20898269,
        "total" : 263651520961
      },
      "totalNumberOfFiles" : 53,
      "totalNumberOfFilesIndexedByExtensions" : 0,
      "totalFilesSize" : 1811154,
      "indexingSpeed" : {
        "totalBytes" : 1811154,
        "totalTime" : 20898269
      },
      "snapshotInputMappingStats" : {
        "totalRequests" : 0,
        "totalMisses" : 0,
        "totalHits" : 0
      }
    }, {
      "indexId" : "json.file.root.values",
      "partOfTotalIndexingTime" : {
        "part" : 18549803,
        "total" : 263651520961
      },
      "totalNumberOfFiles" : 4,
      "totalNumberOfFilesIndexedByExtensions" : 0,
      "totalFilesSize" : 278204,
      "indexingSpeed" : {
        "totalBytes" : 278204,
        "totalTime" : 18549803
      },
      "snapshotInputMappingStats" : {
        "totalRequests" : 0,
        "totalMisses" : 0,
        "totalHits" : 0
      }
    }, {
      "indexId" : "java.source.module.name",
      "partOfTotalIndexingTime" : {
        "part" : 7267323,
        "total" : 263651520961
      },
      "totalNumberOfFiles" : 47,
      "totalNumberOfFilesIndexedByExtensions" : 0,
      "totalFilesSize" : 30265,
      "indexingSpeed" : {
        "totalBytes" : 30265,
        "totalTime" : 7267323
      },
      "snapshotInputMappingStats" : {
        "totalRequests" : 0,
        "totalMisses" : 0,
        "totalHits" : 0
      }
    }, {
      "indexId" : "org.jetbrains.kotlin.idea.vfilefinder.KotlinStdlibIndex",
      "partOfTotalIndexingTime" : {
        "part" : 4101939,
        "total" : 263651520961
      },
      "totalNumberOfFiles" : 47,
      "totalNumberOfFilesIndexedByExtensions" : 0,
      "totalFilesSize" : 30265,
      "indexingSpeed" : {
        "totalBytes" : 30265,
        "totalTime" : 4101939
      },
      "snapshotInputMappingStats" : {
        "totalRequests" : 0,
        "totalMisses" : 0,
        "totalHits" : 0
      }
    }, {
      "indexId" : "org.jetbrains.kotlin.idea.versions.KotlinJsMetadataVersionIndex",
      "partOfTotalIndexingTime" : {
        "part" : 4079922,
        "total" : 263651520961
      },
      "totalNumberOfFiles" : 8,
      "totalNumberOfFilesIndexedByExtensions" : 0,
      "totalFilesSize" : 530727,
      "indexingSpeed" : {
        "totalBytes" : 530727,
        "totalTime" : 4079922
      },
      "snapshotInputMappingStats" : {
        "totalRequests" : 0,
        "totalMisses" : 0,
        "totalHits" : 0
      }
    }, {
      "indexId" : "java.null.method.argument",
      "partOfTotalIndexingTime" : {
        "part" : 3969510,
        "total" : 263651520961
      },
      "totalNumberOfFiles" : 2,
      "totalNumberOfFilesIndexedByExtensions" : 0,
      "totalFilesSize" : 7445,
      "indexingSpeed" : {
        "totalBytes" : 7445,
        "totalTime" : 3969510
      },
      "snapshotInputMappingStats" : {
        "totalRequests" : 0,
        "totalMisses" : 0,
        "totalHits" : 0
      }
    }, {
      "indexId" : "org.jetbrains.kotlin.idea.vfilefinder.KotlinJvmModuleAnnotationsIndex",
      "partOfTotalIndexingTime" : {
        "part" : 3505311,
        "total" : 263651520961
      },
      "totalNumberOfFiles" : 19,
      "totalNumberOfFilesIndexedByExtensions" : 0,
      "totalFilesSize" : 4857,
      "indexingSpeed" : {
        "totalBytes" : 4857,
        "totalTime" : 3505311
      },
      "snapshotInputMappingStats" : {
        "totalRequests" : 0,
        "totalMisses" : 0,
        "totalHits" : 0
      }
    }, {
      "indexId" : "java.binary.plus.expression",
      "partOfTotalIndexingTime" : {
        "part" : 2914174,
        "total" : 263651520961
      },
      "totalNumberOfFiles" : 2,
      "totalNumberOfFilesIndexedByExtensions" : 0,
      "totalFilesSize" : 7445,
      "indexingSpeed" : {
        "totalBytes" : 7445,
        "totalTime" : 2914174
      },
      "snapshotInputMappingStats" : {
        "totalRequests" : 0,
        "totalMisses" : 0,
        "totalHits" : 0
      }
    }, {
      "indexId" : "fileIncludes",
      "partOfTotalIndexingTime" : {
        "part" : 2005248,
        "total" : 263651520961
      },
      "totalNumberOfFiles" : 2,
      "totalNumberOfFilesIndexedByExtensions" : 0,
      "totalFilesSize" : 47677,
      "indexingSpeed" : {
        "totalBytes" : 47677,
        "totalTime" : 2005248
      },
      "snapshotInputMappingStats" : {
        "totalRequests" : 0,
        "totalMisses" : 0,
        "totalHits" : 0
      }
    }, {
      "indexId" : "XsltSymbolIndex",
      "partOfTotalIndexingTime" : {
        "part" : 228151,
        "total" : 263651520961
      },
      "totalNumberOfFiles" : 2,
      "totalNumberOfFilesIndexedByExtensions" : 0,
      "totalFilesSize" : 47677,
      "indexingSpeed" : {
        "totalBytes" : 47677,
        "totalTime" : 228151
      },
      "snapshotInputMappingStats" : {
        "totalRequests" : 0,
        "totalMisses" : 0,
        "totalHits" : 0
      }
    }, {
      "indexId" : "RelaxSymbolIndex",
      "partOfTotalIndexingTime" : {
        "part" : 227876,
        "total" : 263651520961
      },
      "totalNumberOfFiles" : 2,
      "totalNumberOfFilesIndexedByExtensions" : 0,
      "totalFilesSize" : 47677,
      "indexingSpeed" : {
        "totalBytes" : 47677,
        "totalTime" : 227876
      },
      "snapshotInputMappingStats" : {
        "totalRequests" : 0,
        "totalMisses" : 0,
        "totalHits" : 0
      }
    } ],
    "scanningStatistics" : [ {
      "providerName" : "Library Gradle: com.jetbrains:ideaIC:2022.2",
      "numberOfScannedFiles" : 189585,
      "numberOfSkippedFiles" : 2,
      "numberOfFilesForIndexing" : 180884,
      "numberOfFilesFullyIndexedByInfrastructureExtensions" : 0,
      "filesFullyIndexedByInfrastructureExtensions" : [ ],
      "statusTime" : 5937929558,
      "scanningTime" : 6177323811,
      "timeProcessingUpToDateFiles" : 0,
      "timeUpdatingContentLessIndexes" : 137710402,
      "timeIndexingWithoutContent" : 567561934,
      "roots" : [ ]
    }, {
      "providerName" : "JDK openjdk-21",
      "numberOfScannedFiles" : 43903,
      "numberOfSkippedFiles" : 0,
      "numberOfFilesForIndexing" : 43573,
      "numberOfFilesFullyIndexedByInfrastructureExtensions" : 0,
      "filesFullyIndexedByInfrastructureExtensions" : [ ],
      "statusTime" : 3189759469,
      "scanningTime" : 3313358772,
      "timeProcessingUpToDateFiles" : 0,
      "timeUpdatingContentLessIndexes" : 53837866,
      "timeIndexingWithoutContent" : 350651285,
      "roots" : [ ]
    }, {
      "providerName" : "Module 'DiffVerificate' (DiffVerificate)",
      "numberOfScannedFiles" : 18,
      "numberOfSkippedFiles" : 0,
      "numberOfFilesForIndexing" : 8,
      "numberOfFilesFullyIndexedByInfrastructureExtensions" : 0,
      "filesFullyIndexedByInfrastructureExtensions" : [ ],
      "statusTime" : 872974865,
      "scanningTime" : 896062915,
      "timeProcessingUpToDateFiles" : 0,
      "timeUpdatingContentLessIndexes" : 333215,
      "timeIndexingWithoutContent" : 142281,
      "roots" : [ ]
    }, {
      "providerName" : "Indexable set contributor 'com.intellij.javaee.ExternalResourcesRootsProvider@70ea837f' (non-project)",
      "numberOfScannedFiles" : 229,
      "numberOfSkippedFiles" : 4,
      "numberOfFilesForIndexing" : 229,
      "numberOfFilesFullyIndexedByInfrastructureExtensions" : 0,
      "filesFullyIndexedByInfrastructureExtensions" : [ ],
      "statusTime" : 449723154,
      "scanningTime" : 453816680,
      "timeProcessingUpToDateFiles" : 0,
      "timeUpdatingContentLessIndexes" : 784064,
      "timeIndexingWithoutContent" : 4707318,
      "roots" : [ ]
    }, {
      "providerName" : "Library Gradle: org.junit.jupiter:junit-jupiter-params:5.9.3",
      "numberOfScannedFiles" : 403,
      "numberOfSkippedFiles" : 0,
      "numberOfFilesForIndexing" : 403,
      "numberOfFilesFullyIndexedByInfrastructureExtensions" : 0,
      "filesFullyIndexedByInfrastructureExtensions" : [ ],
      "statusTime" : 243713221,
      "scanningTime" : 269438959,
      "timeProcessingUpToDateFiles" : 0,
      "timeUpdatingContentLessIndexes" : 2239074,
      "timeIndexingWithoutContent" : 14607483,
      "roots" : [ ]
    }, {
      "providerName" : "Library Gradle: org.junit.jupiter:junit-jupiter-api:5.9.3",
      "numberOfScannedFiles" : 334,
      "numberOfSkippedFiles" : 0,
      "numberOfFilesForIndexing" : 334,
      "numberOfFilesFullyIndexedByInfrastructureExtensions" : 0,
      "filesFullyIndexedByInfrastructureExtensions" : [ ],
      "statusTime" : 220469218,
      "scanningTime" : 244708225,
      "timeProcessingUpToDateFiles" : 0,
      "timeUpdatingContentLessIndexes" : 1758895,
      "timeIndexingWithoutContent" : 14054708,
      "roots" : [ ]
    }, {
      "providerName" : "Library Gradle: org.junit.jupiter:junit-jupiter-engine:5.9.3",
      "numberOfScannedFiles" : 243,
      "numberOfSkippedFiles" : 0,
      "numberOfFilesForIndexing" : 243,
      "numberOfFilesFullyIndexedByInfrastructureExtensions" : 0,
      "filesFullyIndexedByInfrastructureExtensions" : [ ],
      "statusTime" : 168356336,
      "scanningTime" : 173910187,
      "timeProcessingUpToDateFiles" : 0,
      "timeUpdatingContentLessIndexes" : 1069733,
      "timeIndexingWithoutContent" : 6909573,
      "roots" : [ ]
    }, {
      "providerName" : "Library Gradle: junit:junit:4.13.2",
      "numberOfScannedFiles" : 578,
      "numberOfSkippedFiles" : 0,
      "numberOfFilesForIndexing" : 574,
      "numberOfFilesFullyIndexedByInfrastructureExtensions" : 0,
      "filesFullyIndexedByInfrastructureExtensions" : [ ],
      "statusTime" : 159607699,
      "scanningTime" : 168490145,
      "timeProcessingUpToDateFiles" : 0,
      "timeUpdatingContentLessIndexes" : 1754846,
      "timeIndexingWithoutContent" : 27105228,
      "roots" : [ ]
    }, {
      "providerName" : "Library Gradle: org.junit.platform:junit-platform-engine:1.9.3",
      "numberOfScannedFiles" : 228,
      "numberOfSkippedFiles" : 0,
      "numberOfFilesForIndexing" : 228,
      "numberOfFilesFullyIndexedByInfrastructureExtensions" : 0,
      "filesFullyIndexedByInfrastructureExtensions" : [ ],
      "statusTime" : 116865692,
      "scanningTime" : 121889562,
      "timeProcessingUpToDateFiles" : 0,
      "timeUpdatingContentLessIndexes" : 733759,
      "timeIndexingWithoutContent" : 6120490,
      "roots" : [ ]
    }, {
      "providerName" : "Library Gradle: org.jetbrains:annotations:24.0.0",
      "numberOfScannedFiles" : 93,
      "numberOfSkippedFiles" : 0,
      "numberOfFilesForIndexing" : 93,
      "numberOfFilesFullyIndexedByInfrastructureExtensions" : 0,
      "filesFullyIndexedByInfrastructureExtensions" : [ ],
      "statusTime" : 78471175,
      "scanningTime" : 111857516,
      "timeProcessingUpToDateFiles" : 0,
      "timeUpdatingContentLessIndexes" : 713452,
      "timeIndexingWithoutContent" : 4580128,
      "roots" : [ ]
    }, {
      "providerName" : "Library Gradle: org.junit.platform:junit-platform-commons:1.9.3",
      "numberOfScannedFiles" : 93,
      "numberOfSkippedFiles" : 0,
      "numberOfFilesForIndexing" : 93,
      "numberOfFilesFullyIndexedByInfrastructureExtensions" : 0,
      "filesFullyIndexedByInfrastructureExtensions" : [ ],
      "statusTime" : 62607027,
      "scanningTime" : 86337588,
      "timeProcessingUpToDateFiles" : 0,
      "timeUpdatingContentLessIndexes" : 695880,
      "timeIndexingWithoutContent" : 15792571,
      "roots" : [ ]
    }, {
      "providerName" : "Library Gradle: org.junit.vintage:junit-vintage-engine:5.9.3",
      "numberOfScannedFiles" : 75,
      "numberOfSkippedFiles" : 0,
      "numberOfFilesForIndexing" : 75,
      "numberOfFilesFullyIndexedByInfrastructureExtensions" : 0,
      "filesFullyIndexedByInfrastructureExtensions" : [ ],
      "statusTime" : 44959574,
      "scanningTime" : 61715512,
      "timeProcessingUpToDateFiles" : 0,
      "timeUpdatingContentLessIndexes" : 811547,
      "timeIndexingWithoutContent" : 1849819,
      "roots" : [ ]
    }, {
      "providerName" : "Module 'DiffVerificate.main' (main)",
      "numberOfScannedFiles" : 13,
      "numberOfSkippedFiles" : 0,
      "numberOfFilesForIndexing" : 10,
      "numberOfFilesFullyIndexedByInfrastructureExtensions" : 0,
      "filesFullyIndexedByInfrastructureExtensions" : [ ],
      "statusTime" : 28889713,
      "scanningTime" : 41399126,
      "timeProcessingUpToDateFiles" : 0,
      "timeUpdatingContentLessIndexes" : 9940041,
      "timeIndexingWithoutContent" : 1224625,
      "roots" : [ ]
    }, {
      "providerName" : "Library Gradle: org.apiguardian:apiguardian-api:1.1.2",
      "numberOfScannedFiles" : 9,
      "numberOfSkippedFiles" : 0,
      "numberOfFilesForIndexing" : 9,
      "numberOfFilesFullyIndexedByInfrastructureExtensions" : 0,
      "filesFullyIndexedByInfrastructureExtensions" : [ ],
      "statusTime" : 23945212,
      "scanningTime" : 34565364,
      "timeProcessingUpToDateFiles" : 0,
      "timeUpdatingContentLessIndexes" : 98860,
      "timeIndexingWithoutContent" : 426989,
      "roots" : [ ]
    }, {
      "providerName" : "Library Gradle: org.hamcrest:hamcrest-core:1.3",
      "numberOfScannedFiles" : 88,
      "numberOfSkippedFiles" : 0,
      "numberOfFilesForIndexing" : 88,
      "numberOfFilesFullyIndexedByInfrastructureExtensions" : 0,
      "filesFullyIndexedByInfrastructureExtensions" : [ ],
      "statusTime" : 31235742,
      "scanningTime" : 33459876,
      "timeProcessingUpToDateFiles" : 0,
      "timeUpdatingContentLessIndexes" : 298682,
      "timeIndexingWithoutContent" : 1987338,
      "roots" : [ ]
    }, {
      "providerName" : "Library Gradle: org.opentest4j:opentest4j:1.2.0",
      "numberOfScannedFiles" : 16,
      "numberOfSkippedFiles" : 0,
      "numberOfFilesForIndexing" : 16,
      "numberOfFilesFullyIndexedByInfrastructureExtensions" : 0,
      "filesFullyIndexedByInfrastructureExtensions" : [ ],
      "statusTime" : 10689298,
      "scanningTime" : 12823079,
      "timeProcessingUpToDateFiles" : 0,
      "timeUpdatingContentLessIndexes" : 148861,
      "timeIndexingWithoutContent" : 699061,
      "roots" : [ ]
    }, {
      "providerName" : "Indexable set contributor 'Scratches & Consoles' (non-project)",
      "numberOfScannedFiles" : 1,
      "numberOfSkippedFiles" : 0,
      "numberOfFilesForIndexing" : 1,
      "numberOfFilesFullyIndexedByInfrastructureExtensions" : 0,
      "filesFullyIndexedByInfrastructureExtensions" : [ ],
      "statusTime" : 1505230,
      "scanningTime" : 4080971,
      "timeProcessingUpToDateFiles" : 0,
      "timeUpdatingContentLessIndexes" : 1928,
      "timeIndexingWithoutContent" : 11909,
      "roots" : [ ]
    }, {
      "providerName" : "Indexable set contributor 'Scratches & Consoles' (project)",
      "numberOfScannedFiles" : 0,
      "numberOfSkippedFiles" : 0,
      "numberOfFilesForIndexing" : 0,
      "numberOfFilesFullyIndexedByInfrastructureExtensions" : 0,
      "filesFullyIndexedByInfrastructureExtensions" : [ ],
      "statusTime" : 0,
      "scanningTime" : 0,
      "timeProcessingUpToDateFiles" : 0,
      "timeUpdatingContentLessIndexes" : 0,
      "timeIndexingWithoutContent" : 0,
      "roots" : [ ]
    }, {
      "providerName" : "Indexable set contributor 'com.intellij.javaee.ExternalResourcesRootsProvider@70ea837f' (project)",
      "numberOfScannedFiles" : 0,
      "numberOfSkippedFiles" : 0,
      "numberOfFilesForIndexing" : 0,
      "numberOfFilesFullyIndexedByInfrastructureExtensions" : 0,
      "filesFullyIndexedByInfrastructureExtensions" : [ ],
      "statusTime" : 0,
      "scanningTime" : 0,
      "timeProcessingUpToDateFiles" : 0,
      "timeUpdatingContentLessIndexes" : 0,
      "timeIndexingWithoutContent" : 0,
      "roots" : [ ]
    } ],
    "fileProviderStatistics" : [ {
      "providerName" : "Library Gradle: com.jetbrains:ideaIC:2022.2",
      "totalNumberOfIndexedFiles" : 180884,
      "totalNumberOfFilesFullyIndexedByExtensions" : 0,
      "totalIndexingVisibleTime" : 120603279982,
      "contentLoadingVisibleTime" : 12230293987,
      "numberOfTooLargeForIndexingFiles" : 0,
      "slowIndexedFiles" : [ {
        "fileName" : "GlobalObjects.json",
        "processingTime" : 554993130,
        "indexingTime" : 404249404,
        "contentLoadingTime" : 6571436
      }, {
        "fileName" : "WebApi-l.json",
        "processingTime" : 730060146,
        "indexingTime" : 498305382,
        "contentLoadingTime" : 10073438
      }, {
        "fileName" : "UAX29URLEmailTokenizerImpl.class",
        "processingTime" : 591267415,
        "indexingTime" : 561060025,
        "contentLoadingTime" : 12317920
      }, {
        "fileName" : "html5.html",
        "processingTime" : 761226121,
        "indexingTime" : 702754883,
        "contentLoadingTime" : 6395232
      }, {
        "fileName" : "WebApi-e.json",
        "processingTime" : 760153750,
        "indexingTime" : 520621152,
        "contentLoadingTime" : 12930276
      }, {
        "fileName" : "WebApi-r.json",
        "processingTime" : 689180854,
        "indexingTime" : 488892919,
        "contentLoadingTime" : 11128396
      }, {
        "fileName" : "_Arrays.kt",
        "processingTime" : 943268057,
        "indexingTime" : 909829595,
        "contentLoadingTime" : 14260091
      } ],
      "filesFullyIndexedByExtensions" : [ ],
      "isAppliedAllValuesSeparately" : true,
      "separateApplyingIndexesVisibleTime" : 35798500881
    }, {
      "providerName" : "JDK openjdk-21",
      "totalNumberOfIndexedFiles" : 43573,
      "totalNumberOfFilesFullyIndexedByExtensions" : 0,
      "totalIndexingVisibleTime" : 30913393270,
      "contentLoadingVisibleTime" : 2395522717,
      "numberOfTooLargeForIndexingFiles" : 0,
      "slowIndexedFiles" : [ {
        "fileName" : "KeyIndex$KeyIndexIterator.class",
        "processingTime" : 523893414,
        "indexingTime" : 578230,
        "contentLoadingTime" : 522010617
      }, {
        "fileName" : "EmptyFilter.class",
        "processingTime" : 524038284,
        "indexingTime" : 1009533,
        "contentLoadingTime" : 521986862
      }, {
        "fileName" : "StepIterator.class",
        "processingTime" : 525645567,
        "indexingTime" : 1139387,
        "contentLoadingTime" : 521998285
      }, {
        "fileName" : "NthIterator.class",
        "processingTime" : 525788930,
        "indexingTime" : 1172898,
        "contentLoadingTime" : 522027142
      }, {
        "fileName" : "GB18030.java",
        "processingTime" : 588316536,
        "indexingTime" : 135605627,
        "contentLoadingTime" : 16602553
      } ],
      "filesFullyIndexedByExtensions" : [ ],
      "isAppliedAllValuesSeparately" : true,
      "separateApplyingIndexesVisibleTime" : 15530286633
    }, {
      "providerName" : "Library Gradle: org.junit.platform:junit-platform-engine:1.9.3",
      "totalNumberOfIndexedFiles" : 228,
      "totalNumberOfFilesFullyIndexedByExtensions" : 0,
      "totalIndexingVisibleTime" : 820288232,
      "contentLoadingVisibleTime" : 39873545,
      "numberOfTooLargeForIndexingFiles" : 0,
      "slowIndexedFiles" : [ ],
      "filesFullyIndexedByExtensions" : [ ],
      "isAppliedAllValuesSeparately" : true,
      "separateApplyingIndexesVisibleTime" : 120361270
    }, {
      "providerName" : "Indexable set contributor 'com.intellij.javaee.ExternalResourcesRootsProvider@70ea837f' (non-project)",
      "totalNumberOfIndexedFiles" : 229,
      "totalNumberOfFilesFullyIndexedByExtensions" : 0,
      "totalIndexingVisibleTime" : 608721012,
      "contentLoadingVisibleTime" : 69085785,
      "numberOfTooLargeForIndexingFiles" : 0,
      "slowIndexedFiles" : [ ],
      "filesFullyIndexedByExtensions" : [ ],
      "isAppliedAllValuesSeparately" : true,
      "separateApplyingIndexesVisibleTime" : 166694864
    }, {
      "providerName" : "Library Gradle: org.junit.jupiter:junit-jupiter-api:5.9.3",
      "totalNumberOfIndexedFiles" : 334,
      "totalNumberOfFilesFullyIndexedByExtensions" : 0,
      "totalIndexingVisibleTime" : 583357150,
      "contentLoadingVisibleTime" : 50485987,
      "numberOfTooLargeForIndexingFiles" : 0,
      "slowIndexedFiles" : [ ],
      "filesFullyIndexedByExtensions" : [ ],
      "isAppliedAllValuesSeparately" : true,
      "separateApplyingIndexesVisibleTime" : 113664682
    }, {
      "providerName" : "Library Gradle: junit:junit:4.13.2",
      "totalNumberOfIndexedFiles" : 574,
      "totalNumberOfFilesFullyIndexedByExtensions" : 0,
      "totalIndexingVisibleTime" : 515663904,
      "contentLoadingVisibleTime" : 52630684,
      "numberOfTooLargeForIndexingFiles" : 0,
      "slowIndexedFiles" : [ ],
      "filesFullyIndexedByExtensions" : [ ],
      "isAppliedAllValuesSeparately" : true,
      "separateApplyingIndexesVisibleTime" : 137902194
    }, {
      "providerName" : "Library Gradle: org.junit.jupiter:junit-jupiter-params:5.9.3",
      "totalNumberOfIndexedFiles" : 403,
      "totalNumberOfFilesFullyIndexedByExtensions" : 0,
      "totalIndexingVisibleTime" : 259899525,
      "contentLoadingVisibleTime" : 37023340,
      "numberOfTooLargeForIndexingFiles" : 0,
      "slowIndexedFiles" : [ ],
      "filesFullyIndexedByExtensions" : [ ],
      "isAppliedAllValuesSeparately" : true,
      "separateApplyingIndexesVisibleTime" : 67283004
    }, {
      "providerName" : "Library Gradle: org.jetbrains:annotations:24.0.0",
      "totalNumberOfIndexedFiles" : 93,
      "totalNumberOfFilesFullyIndexedByExtensions" : 0,
      "totalIndexingVisibleTime" : 126197744,
      "contentLoadingVisibleTime" : 22718764,
      "numberOfTooLargeForIndexingFiles" : 0,
      "slowIndexedFiles" : [ ],
      "filesFullyIndexedByExtensions" : [ ],
      "isAppliedAllValuesSeparately" : true,
      "separateApplyingIndexesVisibleTime" : 28814202
    }, {
      "providerName" : "Library Gradle: org.junit.jupiter:junit-jupiter-engine:5.9.3",
      "totalNumberOfIndexedFiles" : 243,
      "totalNumberOfFilesFullyIndexedByExtensions" : 0,
      "totalIndexingVisibleTime" : 110138037,
      "contentLoadingVisibleTime" : 15565722,
      "numberOfTooLargeForIndexingFiles" : 0,
      "slowIndexedFiles" : [ ],
      "filesFullyIndexedByExtensions" : [ ],
      "isAppliedAllValuesSeparately" : true,
      "separateApplyingIndexesVisibleTime" : 41520712
    }, {
      "providerName" : "Library Gradle: org.hamcrest:hamcrest-core:1.3",
      "totalNumberOfIndexedFiles" : 88,
      "totalNumberOfFilesFullyIndexedByExtensions" : 0,
      "totalIndexingVisibleTime" : 103990938,
      "contentLoadingVisibleTime" : 9094714,
      "numberOfTooLargeForIndexingFiles" : 0,
      "slowIndexedFiles" : [ ],
      "filesFullyIndexedByExtensions" : [ ],
      "isAppliedAllValuesSeparately" : true,
      "separateApplyingIndexesVisibleTime" : 46099713
    }, {
      "providerName" : "Module 'DiffVerificate' (DiffVerificate)",
      "totalNumberOfIndexedFiles" : 8,
      "totalNumberOfFilesFullyIndexedByExtensions" : 0,
      "totalIndexingVisibleTime" : 78292767,
      "contentLoadingVisibleTime" : 939090,
      "numberOfTooLargeForIndexingFiles" : 0,
      "slowIndexedFiles" : [ ],
      "filesFullyIndexedByExtensions" : [ ],
      "isAppliedAllValuesSeparately" : true,
      "separateApplyingIndexesVisibleTime" : 2177394
    }, {
      "providerName" : "Library Gradle: org.junit.platform:junit-platform-commons:1.9.3",
      "totalNumberOfIndexedFiles" : 93,
      "totalNumberOfFilesFullyIndexedByExtensions" : 0,
      "totalIndexingVisibleTime" : 52027804,
      "contentLoadingVisibleTime" : 6949007,
      "numberOfTooLargeForIndexingFiles" : 0,
      "slowIndexedFiles" : [ ],
      "filesFullyIndexedByExtensions" : [ ],
      "isAppliedAllValuesSeparately" : true,
      "separateApplyingIndexesVisibleTime" : 19509655
    }, {
      "providerName" : "Module 'DiffVerificate.main' (main)",
      "totalNumberOfIndexedFiles" : 10,
      "totalNumberOfFilesFullyIndexedByExtensions" : 0,
      "totalIndexingVisibleTime" : 47273975,
      "contentLoadingVisibleTime" : 2474611,
      "numberOfTooLargeForIndexingFiles" : 0,
      "slowIndexedFiles" : [ ],
      "filesFullyIndexedByExtensions" : [ ],
      "isAppliedAllValuesSeparately" : true,
      "separateApplyingIndexesVisibleTime" : 7050905
    }, {
      "providerName" : "Library Gradle: org.junit.vintage:junit-vintage-engine:5.9.3",
      "totalNumberOfIndexedFiles" : 75,
      "totalNumberOfFilesFullyIndexedByExtensions" : 0,
      "totalIndexingVisibleTime" : 38148845,
      "contentLoadingVisibleTime" : 6173680,
      "numberOfTooLargeForIndexingFiles" : 0,
      "slowIndexedFiles" : [ ],
      "filesFullyIndexedByExtensions" : [ ],
      "isAppliedAllValuesSeparately" : true,
      "separateApplyingIndexesVisibleTime" : 10832978
    }, {
      "providerName" : "Library Gradle: org.opentest4j:opentest4j:1.2.0",
      "totalNumberOfIndexedFiles" : 16,
      "totalNumberOfFilesFullyIndexedByExtensions" : 0,
      "totalIndexingVisibleTime" : 8838680,
      "contentLoadingVisibleTime" : 1881233,
      "numberOfTooLargeForIndexingFiles" : 0,
      "slowIndexedFiles" : [ ],
      "filesFullyIndexedByExtensions" : [ ],
      "isAppliedAllValuesSeparately" : true,
      "separateApplyingIndexesVisibleTime" : 2871805
    }, {
      "providerName" : "Library Gradle: org.apiguardian:apiguardian-api:1.1.2",
      "totalNumberOfIndexedFiles" : 9,
      "totalNumberOfFilesFullyIndexedByExtensions" : 0,
      "totalIndexingVisibleTime" : 7161691,
      "contentLoadingVisibleTime" : 895602,
      "numberOfTooLargeForIndexingFiles" : 0,
      "slowIndexedFiles" : [ ],
      "filesFullyIndexedByExtensions" : [ ],
      "isAppliedAllValuesSeparately" : true,
      "separateApplyingIndexesVisibleTime" : 3337093
    }, {
      "providerName" : "Indexable set contributor 'Scratches & Consoles' (non-project)",
      "totalNumberOfIndexedFiles" : 1,
      "totalNumberOfFilesFullyIndexedByExtensions" : 0,
      "totalIndexingVisibleTime" : 899644,
      "contentLoadingVisibleTime" : 252202,
      "numberOfTooLargeForIndexingFiles" : 0,
      "slowIndexedFiles" : [ ],
      "filesFullyIndexedByExtensions" : [ ],
      "isAppliedAllValuesSeparately" : true,
      "separateApplyingIndexesVisibleTime" : 185216
    } ],
    "visibleTimeToAllThreadTimeRatio" : 0.25759882710651305
  }
}