{
  "appInfo" : {
    "build" : "222.3345.118",
    "buildDate" : "2022-07-26T05:01:31.303Z[UTC]",
    "productCode" : "IC",
    "generated" : "2024-01-21T09:24:53.622326Z",
    "os" : "macOS 12.7.1",
    "runtime" : "JetBrains s.r.o. 17.0.3 17.0.3+7-b469.32"
  },
  "runtimeInfo" : {
    "maxMemory" : 786432000,
    "numberOfProcessors" : 8,
    "maxNumberOfIndexingThreads" : 4,
    "maxSizeOfFileForIntelliSense" : 2560000,
    "maxSizeOfFileForContentLoading" : 20971520
  },
  "projectIndexingHistory" : {
    "projectName" : "DiffVerificate",
    "times" : {
      "indexingReason" : "On project open",
      "scanningType" : "PARTIAL",
      "totalUpdatingTime" : 12365571624,
      "indexingTime" : 0,
      "contentLoadingVisibleTime" : 0,
      "creatingIteratorsTime" : 10067000,
      "scanFilesTime" : 12307963000,
      "pushPropertiesTime" : 65000,
      "indexExtensionsTime" : 0,
      "isAppliedAllValuesSeparately" : true,
      "separateApplyingIndexesVisibleTime" : 0,
      "updatingStart" : "2024-01-21T09:24:41.243887Z",
      "updatingEnd" : "2024-01-21T09:24:53.610613Z",
      "totalSuspendedTime" : 0,
      "wasInterrupted" : false
    },
    "fileCount" : {
      "numberOfFileProviders" : 21,
      "numberOfScannedFiles" : 290081,
      "numberOfFilesIndexedByInfrastructureExtensionsDuringScan" : 0,
      "numberOfFilesScheduledForIndexingAfterScan" : 0,
      "numberOfFilesIndexedByInfrastructureExtensionsDuringIndexingStage" : 0,
      "numberOfFilesIndexedWithLoadingContent" : 0
    },
    "totalStatsPerFileType" : [ ],
    "totalStatsPerIndexer" : [ ],
    "scanningStatistics" : [ {
      "providerName" : "Library Gradle: com.jetbrains:ideaIC:2022.2",
      "numberOfScannedFiles" : 189585,
      "numberOfSkippedFiles" : 2,
      "numberOfFilesForIndexing" : 0,
      "numberOfFilesFullyIndexedByInfrastructureExtensions" : 0,
      "filesFullyIndexedByInfrastructureExtensions" : [ ],
      "statusTime" : 7725145056,
      "scanningTime" : 7978226426,
      "timeProcessingUpToDateFiles" : 0,
      "timeUpdatingContentLessIndexes" : 168150738,
      "timeIndexingWithoutContent" : 0,
      "roots" : [ ]
    }, {
      "providerName" : "JDK openjdk-21",
      "numberOfScannedFiles" : 43903,
      "numberOfSkippedFiles" : 0,
      "numberOfFilesForIndexing" : 0,
      "numberOfFilesFullyIndexedByInfrastructureExtensions" : 0,
      "filesFullyIndexedByInfrastructureExtensions" : [ ],
      "statusTime" : 4814713986,
      "scanningTime" : 4936479619,
      "timeProcessingUpToDateFiles" : 0,
      "timeUpdatingContentLessIndexes" : 68063624,
      "timeIndexingWithoutContent" : 0,
      "roots" : [ ]
    }, {
      "providerName" : "Synthetic library 'Kotlin Script dependencies'",
      "numberOfScannedFiles" : 52934,
      "numberOfSkippedFiles" : 0,
      "numberOfFilesForIndexing" : 0,
      "numberOfFilesFullyIndexedByInfrastructureExtensions" : 0,
      "filesFullyIndexedByInfrastructureExtensions" : [ ],
      "statusTime" : 4491493257,
      "scanningTime" : 4648114272,
      "timeProcessingUpToDateFiles" : 0,
      "timeUpdatingContentLessIndexes" : 80893798,
      "timeIndexingWithoutContent" : 0,
      "roots" : [ ]
    }, {
      "providerName" : "Module 'DiffVerificate' (DiffVerificate)",
      "numberOfScannedFiles" : 19,
      "numberOfSkippedFiles" : 0,
      "numberOfFilesForIndexing" : 0,
      "numberOfFilesFullyIndexedByInfrastructureExtensions" : 0,
      "filesFullyIndexedByInfrastructureExtensions" : [ ],
      "statusTime" : 1158701929,
      "scanningTime" : 1188786028,
      "timeProcessingUpToDateFiles" : 0,
      "timeUpdatingContentLessIndexes" : 363702,
      "timeIndexingWithoutContent" : 0,
      "roots" : [ ]
    }, {
      "providerName" : "Indexable set contributor 'com.intellij.javaee.ExternalResourcesRootsProvider@2e9798f8' (non-project)",
      "numberOfScannedFiles" : 229,
      "numberOfSkippedFiles" : 4,
      "numberOfFilesForIndexing" : 0,
      "numberOfFilesFullyIndexedByInfrastructureExtensions" : 0,
      "filesFullyIndexedByInfrastructureExtensions" : [ ],
      "statusTime" : 725684701,
      "scanningTime" : 732446758,
      "timeProcessingUpToDateFiles" : 0,
      "timeUpdatingContentLessIndexes" : 992582,
      "timeIndexingWithoutContent" : 0,
      "roots" : [ ]
    }, {
      "providerName" : "Library Gradle: com.alibaba.fastjson2:fastjson2:2.0.43",
      "numberOfScannedFiles" : 1222,
      "numberOfSkippedFiles" : 0,
      "numberOfFilesForIndexing" : 0,
      "numberOfFilesFullyIndexedByInfrastructureExtensions" : 0,
      "filesFullyIndexedByInfrastructureExtensions" : [ ],
      "statusTime" : 454490311,
      "scanningTime" : 481482101,
      "timeProcessingUpToDateFiles" : 0,
      "timeUpdatingContentLessIndexes" : 14428339,
      "timeIndexingWithoutContent" : 0,
      "roots" : [ ]
    }, {
      "providerName" : "Library Gradle: org.junit.jupiter:junit-jupiter-api:5.9.3",
      "numberOfScannedFiles" : 334,
      "numberOfSkippedFiles" : 0,
      "numberOfFilesForIndexing" : 0,
      "numberOfFilesFullyIndexedByInfrastructureExtensions" : 0,
      "filesFullyIndexedByInfrastructureExtensions" : [ ],
      "statusTime" : 226419864,
      "scanningTime" : 246699263,
      "timeProcessingUpToDateFiles" : 0,
      "timeUpdatingContentLessIndexes" : 2568485,
      "timeIndexingWithoutContent" : 0,
      "roots" : [ ]
    }, {
      "providerName" : "Library Gradle: org.junit.jupiter:junit-jupiter-params:5.9.3",
      "numberOfScannedFiles" : 403,
      "numberOfSkippedFiles" : 0,
      "numberOfFilesForIndexing" : 0,
      "numberOfFilesFullyIndexedByInfrastructureExtensions" : 0,
      "filesFullyIndexedByInfrastructureExtensions" : [ ],
      "statusTime" : 213436777,
      "scanningTime" : 242141965,
      "timeProcessingUpToDateFiles" : 0,
      "timeUpdatingContentLessIndexes" : 2439294,
      "timeIndexingWithoutContent" : 0,
      "roots" : [ ]
    }, {
      "providerName" : "Library Gradle: junit:junit:4.13.2",
      "numberOfScannedFiles" : 578,
      "numberOfSkippedFiles" : 0,
      "numberOfFilesForIndexing" : 0,
      "numberOfFilesFullyIndexedByInfrastructureExtensions" : 0,
      "filesFullyIndexedByInfrastructureExtensions" : [ ],
      "statusTime" : 189886492,
      "scanningTime" : 198433926,
      "timeProcessingUpToDateFiles" : 0,
      "timeUpdatingContentLessIndexes" : 10401618,
      "timeIndexingWithoutContent" : 0,
      "roots" : [ ]
    }, {
      "providerName" : "Library Gradle: org.junit.jupiter:junit-jupiter-engine:5.9.3",
      "numberOfScannedFiles" : 243,
      "numberOfSkippedFiles" : 0,
      "numberOfFilesForIndexing" : 0,
      "numberOfFilesFullyIndexedByInfrastructureExtensions" : 0,
      "filesFullyIndexedByInfrastructureExtensions" : [ ],
      "statusTime" : 137608053,
      "scanningTime" : 143101724,
      "timeProcessingUpToDateFiles" : 0,
      "timeUpdatingContentLessIndexes" : 1639410,
      "timeIndexingWithoutContent" : 0,
      "roots" : [ ]
    }, {
      "providerName" : "Library Gradle: org.junit.platform:junit-platform-engine:1.9.3",
      "numberOfScannedFiles" : 228,
      "numberOfSkippedFiles" : 0,
      "numberOfFilesForIndexing" : 0,
      "numberOfFilesFullyIndexedByInfrastructureExtensions" : 0,
      "filesFullyIndexedByInfrastructureExtensions" : [ ],
      "statusTime" : 130123719,
      "scanningTime" : 135427859,
      "timeProcessingUpToDateFiles" : 0,
      "timeUpdatingContentLessIndexes" : 1323007,
      "timeIndexingWithoutContent" : 0,
      "roots" : [ ]
    }, {
      "providerName" : "Library Gradle: org.jetbrains:annotations:24.0.0",
      "numberOfScannedFiles" : 93,
      "numberOfSkippedFiles" : 0,
      "numberOfFilesForIndexing" : 0,
      "numberOfFilesFullyIndexedByInfrastructureExtensions" : 0,
      "filesFullyIndexedByInfrastructureExtensions" : [ ],
      "statusTime" : 98653010,
      "scanningTime" : 118782696,
      "timeProcessingUpToDateFiles" : 0,
      "timeUpdatingContentLessIndexes" : 933882,
      "timeIndexingWithoutContent" : 0,
      "roots" : [ ]
    }, {
      "providerName" : "Module 'DiffVerificate.main' (main)",
      "numberOfScannedFiles" : 28,
      "numberOfSkippedFiles" : 0,
      "numberOfFilesForIndexing" : 0,
      "numberOfFilesFullyIndexedByInfrastructureExtensions" : 0,
      "filesFullyIndexedByInfrastructureExtensions" : [ ],
      "statusTime" : 83949549,
      "scanningTime" : 117985649,
      "timeProcessingUpToDateFiles" : 0,
      "timeUpdatingContentLessIndexes" : 297331,
      "timeIndexingWithoutContent" : 0,
      "roots" : [ ]
    }, {
      "providerName" : "Library Gradle: org.junit.vintage:junit-vintage-engine:5.9.3",
      "numberOfScannedFiles" : 75,
      "numberOfSkippedFiles" : 0,
      "numberOfFilesForIndexing" : 0,
      "numberOfFilesFullyIndexedByInfrastructureExtensions" : 0,
      "filesFullyIndexedByInfrastructureExtensions" : [ ],
      "statusTime" : 45194650,
      "scanningTime" : 49619556,
      "timeProcessingUpToDateFiles" : 0,
      "timeUpdatingContentLessIndexes" : 293873,
      "timeIndexingWithoutContent" : 0,
      "roots" : [ ]
    }, {
      "providerName" : "Library Gradle: org.junit.platform:junit-platform-commons:1.9.3",
      "numberOfScannedFiles" : 93,
      "numberOfSkippedFiles" : 0,
      "numberOfFilesForIndexing" : 0,
      "numberOfFilesFullyIndexedByInfrastructureExtensions" : 0,
      "filesFullyIndexedByInfrastructureExtensions" : [ ],
      "statusTime" : 38166370,
      "scanningTime" : 47859542,
      "timeProcessingUpToDateFiles" : 0,
      "timeUpdatingContentLessIndexes" : 1180316,
      "timeIndexingWithoutContent" : 0,
      "roots" : [ ]
    }, {
      "providerName" : "Library Gradle: org.hamcrest:hamcrest-core:1.3",
      "numberOfScannedFiles" : 88,
      "numberOfSkippedFiles" : 0,
      "numberOfFilesForIndexing" : 0,
      "numberOfFilesFullyIndexedByInfrastructureExtensions" : 0,
      "filesFullyIndexedByInfrastructureExtensions" : [ ],
      "statusTime" : 31295250,
      "scanningTime" : 33874977,
      "timeProcessingUpToDateFiles" : 0,
      "timeUpdatingContentLessIndexes" : 342100,
      "timeIndexingWithoutContent" : 0,
      "roots" : [ ]
    }, {
      "providerName" : "Library Gradle: org.opentest4j:opentest4j:1.2.0",
      "numberOfScannedFiles" : 16,
      "numberOfSkippedFiles" : 0,
      "numberOfFilesForIndexing" : 0,
      "numberOfFilesFullyIndexedByInfrastructureExtensions" : 0,
      "filesFullyIndexedByInfrastructureExtensions" : [ ],
      "statusTime" : 8033798,
      "scanningTime" : 9111967,
      "timeProcessingUpToDateFiles" : 0,
      "timeUpdatingContentLessIndexes" : 116787,
      "timeIndexingWithoutContent" : 0,
      "roots" : [ ]
    }, {
      "providerName" : "Library Gradle: org.apiguardian:apiguardian-api:1.1.2",
      "numberOfScannedFiles" : 9,
      "numberOfSkippedFiles" : 0,
      "numberOfFilesForIndexing" : 0,
      "numberOfFilesFullyIndexedByInfrastructureExtensions" : 0,
      "filesFullyIndexedByInfrastructureExtensions" : [ ],
      "statusTime" : 5487719,
      "scanningTime" : 6675106,
      "timeProcessingUpToDateFiles" : 0,
      "timeUpdatingContentLessIndexes" : 57630,
      "timeIndexingWithoutContent" : 0,
      "roots" : [ ]
    }, {
      "providerName" : "Indexable set contributor 'Scratches & Consoles' (non-project)",
      "numberOfScannedFiles" : 1,
      "numberOfSkippedFiles" : 0,
      "numberOfFilesForIndexing" : 0,
      "numberOfFilesFullyIndexedByInfrastructureExtensions" : 0,
      "filesFullyIndexedByInfrastructureExtensions" : [ ],
      "statusTime" : 2795918,
      "scanningTime" : 3023101,
      "timeProcessingUpToDateFiles" : 0,
      "timeUpdatingContentLessIndexes" : 3587,
      "timeIndexingWithoutContent" : 0,
      "roots" : [ ]
    }, {
      "providerName" : "Indexable set contributor 'Scratches & Consoles' (project)",
      "numberOfScannedFiles" : 0,
      "numberOfSkippedFiles" : 0,
      "numberOfFilesForIndexing" : 0,
      "numberOfFilesFullyIndexedByInfrastructureExtensions" : 0,
      "filesFullyIndexedByInfrastructureExtensions" : [ ],
      "statusTime" : 0,
      "scanningTime" : 0,
      "timeProcessingUpToDateFiles" : 0,
      "timeUpdatingContentLessIndexes" : 0,
      "timeIndexingWithoutContent" : 0,
      "roots" : [ ]
    }, {
      "providerName" : "Indexable set contributor 'com.intellij.javaee.ExternalResourcesRootsProvider@2e9798f8' (project)",
      "numberOfScannedFiles" : 0,
      "numberOfSkippedFiles" : 0,
      "numberOfFilesForIndexing" : 0,
      "numberOfFilesFullyIndexedByInfrastructureExtensions" : 0,
      "filesFullyIndexedByInfrastructureExtensions" : [ ],
      "statusTime" : 0,
      "scanningTime" : 0,
      "timeProcessingUpToDateFiles" : 0,
      "timeUpdatingContentLessIndexes" : 0,
      "timeIndexingWithoutContent" : 0,
      "roots" : [ ]
    } ],
    "fileProviderStatistics" : [ ],
    "visibleTimeToAllThreadTimeRatio" : 0.0
  }
}